Workbook

Sheet Group Details
A1: SAPM Assignment
A3: Group Details
A4: Name | B4: ID
A5: Kabir Jain | B5: 2023A7PS0542P
A6: Rishi Somani | B6: 2023A1PS0212P
A7: Aditi Sharma | B7: 2023A1PS0184P
A8: Naman Sagtani | B8: 2023A5PS1183P
A11: Company Selected | B11: Tata Elxsi Ltd.
A12: Reason for selection | B12: Tata Elxsi was selected for this project because it is a mid-cap IT company with a unique position in the design and engineering services sector, serving global automotive, healthcare, and technology clients with cutting-edge solutions. Its strong financials, consistent dividend growth, and market leadership within the Tata Group make it an excellent benchmark for studying successful, innovation-driven mid-cap companies in India.

Sheet Part 1 Fundamental Financials
A1: Part 1: Fundamental Financials
A3: Tata Elxsi Ltd.
A4: Industry Classification | B4: IT Services / ER&D / Software development services, system integration & support
A5: Age of Firm | B5: Incorporated in 1989; Operating for 35 years
A6: NIC Code | B6: 62013 (Software Development), 62020 (System Integration)
A7: Market Position | B7: Leading global design and technology services provider
A11: Summary of all required ratios
A12: Ratio | B12: FY 2024-25 | C12: FY 2023-24 | D12: Typical IT/ER&D Industry Average | E12: Better / Worse vs Industry | F12: Brief Interpretation
A13: P/E Ratio | B13: =B48 -> 40.913037 | C13: =C48 -> 60.323481 | D13: ~25–30 | E13: Worse (more expensive) | F13: Trades at a richer multiple than most IT/ER&D peers, implying high expectations baked into price.
A14: EBITDA / Total Assets | B14: =B67/100 -> 0.32134605 | C14: =C67/100 -> 0.36661213 | D14: ~18–22% | E14: Better | F14: Enterprise value per unit of EBITDA is significantly above sector norms, indicating premium valuation.
A15: EV / EBITDA | B15: =B49 -> 27.921212 | C15: =C49 -> 40.979708 | D15: ~16–20 | E15: Worse (more expensive) | F15: Pays a slightly lower yield than many large IT peers despite high payout per share, because price is high.
A16: Intangible Assets / Total Assets | B16: =B80/100 -> 0.0024680137 | C16: =C80/100 -> 0.004217533 | F16: Asset productivity is far superior; the firm converts its asset base into operating profits very efficiently.
A17: Dividend Yield | B17: =B50/100 -> 0.0091208819 | C17: =C50/100 -> 0.010466013 | D17: ~1.2–1.5% | E17: Worse (lower yield) | F17: Keeps more of each rupee of revenue as profit than the typical IT/ER&D company.
A18: Total Liabilities / Total Assets | B18: =B86/100 -> 0.20239985 | C18: =C86/100 -> 0.21378388 | D18: ~16–18% | E18: Better | F18: Overall return on assets is well above sector average, signalling strong operating efficiency.
A19: Source of funding for the company's projects and funding (financing) patterns | B19: In FY 2024–25, the same internal‑funding, low‑debt pattern continued and strengthened. Around 80% of total assets (₹3,58,572 lakhs) were financed by equity (₹2,85,997 lakhs), with liabilities at ~20% and long‑term lease liabilities reduced to ₹13,931 lakhs, again with no material term‑debt. Operating cash flow (~₹81,198 lakhs) easily covered a much lower capex (~₹1,634 lakhs), while financing cash outflows (~₹49,859 lakhs) were mainly higher dividends and lease repayments, confirming that projects are financed out of retained earnings and cash flows rather than external borrowing. | C19: In FY 2023–24, Tata Elxsi’s projects were funded mainly by equity and internal cash flows, with very low external leverage. About 79% of total assets (₹3,18,698 lakhs) were financed by equity (₹2,50,566 lakhs), while liabilities were ~21% and consisted largely of lease and operating liabilities rather than term loans. Net cash from operations (~₹70,123 lakhs) was more than enough to fund capex (~₹8,302 lakhs), and financing cash outflows (~₹42,783 lakhs) were dominated by dividends and lease repayments, indicating no need for fresh debt | F19: Shareholder returns are materially higher than industry, even with low leverage.
A20: Long-term Debt / Total Assets(%) | B20: =B87 -> 3.8852084 | C20: =C87 -> 5.6852854 | D20: ~13–16% | E20: Better | F20: Uses less debt than the average IT firm, giving a very comfortable balance sheet.
A21: Annual Capex / Total Assets | B21: =B76/100 -> 0.004557442 | C21: =C76/100 -> 0.026048252 | D21: ~17–20% | E21: Better | F21: Negligible structural gearing; financial risk from debt is low.
A22: Total Asset Turnover | B22: =B75 -> 1.0399727 | C22: =C75 -> 1.1145799 | D22: ~30–40% | E22: Better (more conservative) | F22: Capital intensity is low; growth is more people/IP-driven than asset-heavy, similar to peers.
A23: Return on Assets (ROA) | B23: =B68/100 -> 0.21890647 | C23: =C68/100 -> 0.24858565 | D23: ~5–10% | E23: Better (less debt) | F23: Much smaller booked intangibles; IP is not aggressively capitalised on the balance sheet.
A24: Growth Rate in Sales (%) | B24: =B70/100 -> 0.049801617 | C24: =C70/100 -> 0.12955776 | D24: ~1–2% | E24: Neutral–slightly lower | F24: Growth has moderated vs both its own history and many peers after sector-wide slowdown.
A25: Gross Profit Margins | B25: =B56/100 -> 0.93599898 | C25: =C56/100 -> 0.94536663 | D25: ~5–10% | E25: Different mix | F25: Very high value‑added nature of services; strong pricing power.
A26: Net Profit Margin | B26: =B58/100 -> 0.21049253 | C26: =C58/100 -> 0.2230308 | D26: ~8–12% | E26: Worse (slower) | F26: Converts earnings to cash well, supporting dividends and optionality for growth.
A27: ROE (DuPont Analysis) | B27: =B93/100 -> 0.27445641 | C27: =C93/100 -> 0.3161798 | D27: ~85–90% | E27: Better
A28: Free Cash Flows (FCF)( Lakhs) | B28: =B102 -> -149789.91 | C28: =C102 -> -137894.28 | D28: absolute, firm‑specific | E28: Better qualitatively
A33: Calculation of all the ratios
A34: Financial Metrics | B34: FY 2024-25 | C34: FY 2023-24 | D34: FY 2022-23 | E34: Source
A35: VALUATION RATIOS
A36: Net Profit (₹ Lakhs) | B36: ='All References'!F52 -> 78493.68 | C36: ='All References'!G52 -> 79223.79 | E36: Income Statement
A37: EPS - Basic (₹) | B37: ='All References'!F59 -> 126.03 | C37: ='All References'!G59 -> 127.21 | E37: Income Statement
A38: EPS - Diluted (₹) | B38: ='All References'!F60 -> 126.01 | C38: ='All References'!G60 -> 127.18 | E38: Income Statement
A39: Total Shares Outstanding | B39: 62284124 | C39: 62276440 | E39: Equity Share Capital in Annual Report
A40: Dividends Paid(Lakhs) | B40: ='All References'!J63 -> 43593.51 | C40: ='All References'!K63 -> 37739.52 | E40: Dividends Paid from Financing Cash Flow Statement
A41: DPS | B41: =B40/B39*100000 -> 69.991367 | C41: =C40/C39*100000 -> 60.599996 | E41: Dividend Paid/Number of Share Outstanding
A42: Adjusted Closing Price of Stock at the end of Fiscal Year | B42: 5156.27 | C42: 7673.75 | D42: 5790.17 | E42: yfinance.com
A43: Long-term Debt | B43: ='All References'!B68 -> 13931.26 | C43: ='All References'!C68 -> 18118.9 | E43: Balance Sheet
A44: Short Term Debt | B44: ='All References'!B73 -> 5297.82 | C44: ='All References'!C73 -> 4279.24 | E44: Balance Sheet
A45: Total Debt | B45: =B43+B44 -> 19229.08 | C45: =C43+C44 -> 22398.14 | E45: Long Term Debt+ Short Term Debt
A46: Market Cap(Lakhs) | B46: =B39*B42/100000 -> 3211537.6 | C46: =C39*C42/100000 -> 4778938.3 | E46: Price*Outstanding Share
A47: Enterprise Value (₹ Lakhs) | B47: =B46+B45-B84 -> 3217239 | C47: =C46+C45-C84 -> 4788012.2 | E47: Market Cap+Total Debt(Long Term+Short Term)-Cash & Cash Equivalent
A48: P/E Ratio | B48: =B42/B37 -> 40.913037 | C48: =C42/C37 -> 60.323481 | E48: Adjusted Closing Price at last trading day of fiscal year /Earnings Per Share
A49: Enterprise Value/EBITDA | B49: =B47/B62 -> 27.921212 | C49: =C47/C62 -> 40.979708 | E49: Enterprise Value/Earnings Before Intrest Tax Depriciation and Amortisation
A50: Dividend Yield(%) | B50: =B41/C42*100 -> 0.91208819 | C50: =C41/D42*100 -> 1.0466013 | E50: Dividend Per Share/Initial Price
A52: PROFITABILITY RATIOS
A53: Revenue from Operations | B53: ='All References'!F36 -> 372904.83 | C53: ='All References'!G36 -> 355214.57 | D53: 314472.25 | E53: Income Statement
A54: Cost of Goods Consumed | B54: ='All References'!F40 -> 23866.29 | C54: ='All References'!G40 -> 19406.57 | E54: Income Statement
A55: Gross Profit | B55: =B53-B54 -> 349038.54 | C55: =C53-C54 -> 335808 | E55: Revnue-Cost of Goods Sold
A56: Gross Profit Margin (in %) | B56: =B55/B53*100 -> 93.599898 | C56: =C55/C53*100 -> 94.536663 | E56: Gross Profit/Revenue*100
A57: Net Profit | B57: ='All References'!F52 -> 78493.68 | C57: ='All References'!G52 -> 79223.79 | E57: Income Statement
A58: Net Profit Margin (%) | B58: =B57/B53*100 -> 21.049253 | C58: =C57/C53*100 -> 22.30308 | E58: Net Profit*100/Revenue
A59: Taxes | B59: ='All References'!F51 -> 24346.72 | C59: ='All References'!G51 -> 25643.81 | E59: Income Statement
A60: Finance Cost | B60: ='All References'!F43 -> 1898.14 | C60: ='All References'!G43 -> 2026.07 | E60: Income Statement
A61: Depriciation and Amortisation | B61: ='All References'!F44 -> 10487.08 | C61: ='All References'!G44 -> 9944.94 | E61: Income Statement
A62: EBITDA | B62: =B57+B59+B60+B61 -> 115225.62 | C62: =C57+C59+C60+C61 -> 116838.61 | E62: Net Profit+Taxes+Finance Costs+Depriciation
A63: EBIT | B63: =B62-B61 -> 104738.54 | C63: =C62-C61 -> 106893.67 | E63: EBITDA-DA
A64: Total Assets | B64: ='All References'!B59 -> 358571.76 | C64: ='All References'!C59 -> 318698.16 | E64: Balance Sheet
A65: Total Equity | B65: ='All References'!B65 -> 285996.89 | C65: ='All References'!C65 -> 250565.63 | E65: Balance Sheet
A66: EBITDA Margin (%) | B66: =B62/B53*100 -> 30.899471 | C66: =C62/C53*100 -> 32.892404 | E66: EBITDA/Revenue*100
A67: EBITDA / Total Assets (%) | B67: =B62/B64*100 -> 32.134605 | C67: =C62/C64*100 -> 36.661213 | E67: EBITDA/Total Assets*100
A68: Return on Asset(ROA)(%) | B68: =B57/B64*100 -> 21.890647 | C68: =C57/C64*100 -> 24.858565 | E68: Net Profit/Total Assets
A69: Return on Equity(ROE)(%) | B69: =B36/B65*100 -> 27.445641 | C69: =C36/C65*100 -> 31.61798 | E69: Net Profit/Total Equity
A70: Growth Rate in Sales(%) | B70: =(B53-C53)/C53*100 -> 4.9801617 | C70: =(C53-D53)/D53*100 -> 12.955776 | E70: (Revenue of current year-Revenue of previous year)/Revenue of Previous year*100
A72: ASSET EFFICIENCY
A73: Current Assets | B73: ='All References'!B58 -> 279749.82 | C73: ='All References'!C58 -> 253672.08 | E73: Balance Sheet
A74: Capex(Lakhs) | B74: ='All References'!J52 -> 1634.17 | C74: ='All References'!K52 -> 8301.53 | E74: Acquistions of PPE & Intangible Assets from Investing Cash Flow Statement
A75: Asset Turnover Ratio | B75: =B53/B64 -> 1.0399727 | C75: =C53/C64 -> 1.1145799 | E75: Total Assets/Revenue from Operations
A76: Capex/Total Assets(%) | B76: =B74/B64*100 -> 0.4557442 | C76: =C74/C64*100 -> 2.6048252 | E76: Capex/Total Assets*100
A78: INTANGIBLE COMPOSITION
A79: Intangible Assets | B79: ='All References'!B41 -> 884.96 | C79: ='All References'!C41 -> 1344.12 | E79: Balance Sheet
A80: Intangible assets/Total assets(%) | B80: =B79/B64*100 -> 0.24680137 | C80: =C79/C64*100 -> 0.4217533 | E80: Intangible Assets/Total Assets*100
A82: LEVERAGE & SOLVENCY
A83: Total Liabilities | B83: ='All References'!B70+'All References'!B80 -> 72574.87 | C83: ='All References'!C70+'All References'!C80 -> 68132.53 | E83: Current Liabilities+Non-Current Liabilities
A84: Cash and Cash Equivalent | B84: ='All References'!B53 -> 13527.66 | C84: ='All References'!C53 -> 13324.29 | E84: Balance Sheet
A85: Current Liabilities | B85: ='All References'!B80 -> 52968.3 | C85: ='All References'!C80 -> 44593.64 | E85: Balance Sheet
A86: Total Liabilities/Total Assets(%) | B86: =B83/B64*100 -> 20.239985 | C86: =C83/C64*100 -> 21.378388 | E86: Total Liabilities/Total Assets*100
A87: Long-term Debt/Total Assets(%) | B87: =B43/B64*100 -> 3.8852084 | C87: =C43/C64*100 -> 5.6852854 | E87: Long-Term Debt/Total Assets*100
A89: DUPONT ANALYSIS
A90: Net Profit Margin(%) | B90: =B58 -> 21.049253 | C90: =C58 -> 22.30308 | D90: =D58 -> 0 | E90: Net Profit*100/Revenue
A91: Asset Turnover | B91: =B75 -> 1.0399727 | C91: =C75 -> 1.1145799 | D91: =D75 -> 0 | E91: Total Assets/Revenue from Operations
A92: Financial Leverage | B92: =B64/B65 -> 1.253761 | C92: =C64/C65 -> 1.2719149 | E92: Total Assets/Total Equity
A93: ROE (NPM × AT × FL)(%) | B93: =B90*B91*B92 -> 27.445641 | C93: =C90*C91*C92 -> 31.61798 | E93: Net Profit Margin*Asset Turnover*Financial Leverage
A95: Free Cash Flow Analysis
A96: Net changes in Operating Working Capital(Lakhs) | B96: =B73-B85 -> 226781.52 | C96: =C73-C85 -> 209078.44 | E96: Current Assets-Current Liabilities
A97: Tax Rate(%) | B97: 34.944 | C97: 34.944 | E97: Income Tax Expense Notes in Annual Report
A98: Capex(Lakhs) | B98: =B74 -> 1634.17 | C98: 8301.53 | E98: Acquistions of PPE & Intangible Assets from Investing Cash Flow Statement
A99: Depriciation and Amortization(Lakhs) | B99: ='All References'!F44 -> 10487.08 | C99: ='All References'!G44 -> 9944.94 | E99: Income Statement
A100: EBIT(Lakhs) | B100: =B63 -> 104738.54 | C100: =C63 -> 106893.67 | E100: EBITDA-DA
A101: NOPAT(Lakhs) | B101: =B100*(1-B97/100) -> 68138.705 | C101: =C100*(1-C97/100) -> 69540.746 | E101: EBIT(1-Tax(%)/100)
A102: Free Cash Flow to Firm | B102: =B101+B99-B98-B96 -> -149789.91 | C102: =C101+C99-C74-C96 -> -137894.28 | E102: NOPAT+Depriciation-Capex-NOWC

Sheet Part 2 Price Movement Analysis
A1: Part 2: Price Movement Analysis
A3: Lifetime High | B3: 10573.23
A4: Lifetime Low | B4: 4700
A5: Current price’s | B5: 5158.5
A6: Current price’s % discount (premium) to lifetime high | B6: =(B3-B5)*100/B3 -> 51.211692
A7: The average volume of shares traded daily over the past 52 weeks | B7: 233084.1
A9: Weekly historical returns over the past one year :-
A10: Week end date | B10: Weekly close (₹) | C10: Weekly return (%)
A11: 45632 | B11: 7396 | C11: –
A12: 45639 | B12: 7364 | C12: -0.43
A13: 45646 | B13: 6922 | C13: -6.01
A14: 45653 | B14: 6886 | C14: -0.52
A15: 45660 | B15: 6648 | C15: -3.46
A16: 45667 | B16: 6001 | C16: -9.71
A17: 45674 | B17: 6212 | C17: 3.52
A18: 45681 | B18: 6373 | C18: 2.59
A19: 45688 | B19: 6336 | C19: -0.58
A20: 45695 | B20: 6371 | C20: 0.55
A21: 45702 | B21: 6285 | C21: -1.35
A22: 45709 | B22: 6198 | C22: -1.39
A23: 45716 | B23: 6265 | C23: 1.08
... A60: 45975 | B60: 5267 | C60: 1.68
A62: Dividend payment history over the past two years – which types of dividends are paid | B62: FY 2023–24: | C62: Final dividend of ₹70 per share (700% on ₹10 face value), declared in April 2024 and paid after the June 2024 record/ex‑date; this is classified as a final cash dividend.
B63: FY 2024–25: | C63: Final dividend of ₹75 per share (750%), recommended by the board in April 2025 and made effective with a June 11, 2025 record date; again, this is a normal final cash dividend.
A64: Stock split history (past two years) | B64: None | C64: No stock split has been carried out in FY 2023‑24 or FY 2024‑25; the face value has remained ₹10 and share‑count changes are negligible, driven by ESOP allotments rather than splits.
A65: Share repurchase (past two years) | B65: None | C65: There is no buyback announcement or execution for Tata Elxsi in the last two financial years in the corporate‑actions or investor‑relations sections. Share count has slightly increased, not decreased, due to ESOPs, which confirms there was no repurchase programme
A66: Mergers and acquisition, any other significant corporate action | B66: None | C66: No major mergers or acquisitions in the last two years; growth has been organic, driven by large strategic contracts and partnerships across automotive (software‑defined vehicles), media and healthcare.
A69: Market reaction to earnings (last 4 quarters, FY24 or FY25)
A70: Quarter (FY) | B70: Result date | C70: Key earnings highlight (revenue / profit) | D70: Dividend / guidance highlight | E70: Market reaction around results (1–3 days) | F70: Interpretation
A71: Q4 FY25 | B71: 17 Apr 2025 , stock move noted 21 Apr 2025 | C71: Revenue about ₹908 crore, down ~3% QoQ and roughly flat YoY; PAT down ~13% QoQ to ~₹172 crore, margins compressed vs prior quarter. | D71: Board recommended final dividend of ₹75 per share (750% of face value) for FY25. | E71: Intraday, share price jumped roughly 5–5.5% after results and dividend announcement, but subsequent days saw only limited net upside as concerns on margin pressure remained. | F71: Positive knee‑jerk reaction to high dividend and stable full‑year numbers, but overall sentiment cautious due to declining QoQ profit and margin compression.
A72: Q3 FY25 | B72: 45665 | C72: Revenue around ₹939 crore; operating profit and PBT at a five‑quarter low, with margins under pressure vs earlier quarters. | D72: No new dividend; management commentary focused on deal wins and investments in digital/AI to drive future growth. | E72: Stock fell on or shortly after results (reports mention the share sinking ~5–7% intraday as weaker profitability surprised the market). | F72: Clearly negative reaction: investors punished deteriorating profitability despite steady topline and pipeline commentary.
A73: Q2 FY25 | B73: 45575 | C73: Q2 revenue broadly stable with low single‑digit growth YoY, but transportation and media segments soft, leading to slower overall growth and some margin slippage. | D73: No interim dividend; commentary stressed cost discipline and medium‑term deal pipeline. | E73: Price response muted to mildly negative over the 1–3 day window, with the stock drifting lower as numbers were seen as “in line to slightly weak”. | F73: Market reaction was neutral‑to‑negative: results were not bad but not strong enough to reverse the ongoing de‑rating.
A74: Q1 FY25 | B74: 45483 | C74: Revenue and PAT up modestly YoY but flat to slightly down QoQ; continued headwinds in key export verticals. | D74: No dividend; management reiterated focus on large deals and diversification. | E74: Stock showed small negative to flat movement after results, with no sustained rally, reflecting already rich multiples and cautious outlook. | F74: Reaction broadly muted: earnings did not trigger buying interest, reinforcing the narrative of valuation compression despite okay fundamentals.

Sheet Part 3 Portfolio Analysis
A1: Part 3: Portfolio Analysis
A2: Portfolio Construction
A3: Portfolio Size: 1 Crore | H3: Bench Mark Index
A4: Stock Name | B4: Tata Elxsi | C4: Reliance Industries | D4: HDFC Bank | E4: Infosys | F4: Trent Ltd. | G4: Overall Portfolio Performance Summary | H4: NIFTY 50 Index | I4: Inference | J4: Extra Information
A5: Sector | B5: IT + Design + ER&D | C5: Conglomerate (Energy + Retail + Telecom) | D5: BFSI | E5: IT & Services | F5: Retail | G5: Multi-Sector Portfolio (IT + Energy + BFSI + IT Services + Retail) | H5: Broad Market Index – Represents top 50 Indian companies across 14 sectors | I5: The portfolio is intentionally diversified across IT, Conglomerates, BFSI, IT Services, and Retail. This cross-sector allocation helps reduce unsystematic risk and ensures that no single industry dominates portfolio volatility.
A6: Notes | B6: High growth, high volatility | C6: Low-risk anchor, stable returns | D6: Low volatility, steady compounder | E6: Stable large-cap IT | F6: High growth potential but higher valuation | G6: Represents the combined outcome of all five selected stocks and gives a consolidated summary of the portfolio’s overall performance. | H6: Chosen as benchmark because it aligns with the portfolio’s sector composition and contains large-cap stocks similar to Reliance, HDFC Bank, Infosys
A7: Market Cap(crores) | B7: 55491 | C7: 1781841 | D7: 820000 | E7: 791100 | F7: 48044 | G7: =SUM(B7:F7) -> 3496476 | I7: Market capitalization estimates a company's value by extrapolating what the market thinks it is worth for publicly traded companies and multiplying the share price by the number of available shares.
A8: Weight(%) | B8: 30 | C8: =0.7*C7/($G$7-$B$7)*100 -> 36.248013 | D8: =0.7*D7/($G$7-$B$7)*100 -> 16.68127 | E8: =0.7*E7/($G$7-$B$7)*100 -> 16.093357 | F8: =0.7*F7/($G$7-$B$7)*100 -> 0.97735968 | G8: =SUM(B8:F8) -> 100 | I8: The 30% allocation to Tata Elxsi reflects its role as the primary stock. Remaining weights are value-weighted across four stable large-cap companies, improving diversification while maintaining exposure to high-growth sectors.
A9: Amount Invested in each stock as on 1 April 2022 | B9: =100000*B8 -> 3000000 | C9: =100000*C8 -> 3624801.3 | D9: =100000*D8 -> 1668127 | E9: =100000*E8 -> 1609335.7 | F9: =100000*F8 -> 97735.968 | G9: =SUM(B9:F9) -> 10000000 | I9: By allocating capital based on initial weights on 1 April 2022 and avoiding rebalancing, the analysis captures the true impact of market movements on long-term portfolio behavior, as instructed.
A10: Number of Shares Purchased on 1 April 2022 | B10: =B9/B13 -> 348.17959 | C10: =C9/C13 -> 2999.5618 | D10: =D9/D13 -> 2328.7777 | E10: =E9/E13 -> 941.77753 | F10: =F9/F13 -> 77.366715 | G10: =SUM(B10:F10) -> 6695.6633 | I10: Amount Invested/Adjusted Closing Price at 1 April 2022. Since portfolio need not to be rebalanced, it will remain constant throughout the time. | J10: Number of shares= Amount invested/Adjusted Closing Price of that stock
A12: Value of Portfolio on different dates
A13: Adjusted Closing Price as on 1 April 2022 | B13: 8616.2432 | C13: 1208.4436 | D13: 716.31012 | E13: 1708.8279 | F13: 1263.2819 | H13: 17670.449 | I13: Adjusted closing prices correctly incorporate splits/dividends and therefore provide an accurate basis for calculating returns, ensuring that performance is not overstated or understated due to corporate actions.
A14: Adjusted Closing Price as on 30 December 2022 | B14: 6107.7002 | C14: 1162.7881 | D14: 783.41327 | E14: 1383.2114 | F14: 1347.2737 | H14: 18105.301
A15: Adjusted Closing Price as on 2 January 2023 | B15: 6121.7891 | C15: 1175.8896 | D15: 783.67786 | E15: 1397.7021 | F15: 1338.1016 | H15: 18197.449
A16: Adjusted Closing Price as on 29 December 2023 | B16: 8571.9746 | C16: 1282.9791 | D16: 831.86755 | E16: 1452.6169 | F16: 3050.2129 | H16: 21731.4
A17: Adjusted Closing Price as on 1 January 2024 | B17: 8562.916 | C17: 1285.6097 | D17: 826.44104 | E17: 1460.5726 | F17: 2997.4451 | H17: 21741.9
A18: Adjusted Closing Price as on 31 December 2024 | B18: 6720.5254 | C18: 1210.6149 | D18: 874.60303 | E18: 1825.9618 | F18: 7117.1841 | H18: 23644.801
A19: Adjusted Closing Price as on 1 January 2025 | B19: 6668.3164 | C19: 1216.3918 | D19: 879.48694 | E19: 1828.39 | F19: 7061.9316 | H19: 23742.9
A20: Adjusted Closing Price as on 28 November 2025 | B20: 5158.5 | C20: 1567.5 | D20: 1007.6 | E20: 1560.1 | F20: 4250.3999 | H20: 26202.949
A21: Value at 1 April 2022 | B21: =B$10*B13 -> 3000000 | C21: =C$10*C13 -> 3624801.3 | D21: =D$10*D13 -> 1668127 | E21: =E$10*E13 -> 1609335.7 | F21: =F$10*F13 -> 97735.968 | G21: =SUM(B21:F21) -> 10000000 | H21: 17670.449 | I21: Initial values are computed based on number of shares purchased. This establishes the portfolio’s cost base and is essential for accurate return measurement. | J21: Value=Adjusted market price*Number of stocks in portfolio
A22: Value at 30 December 2022 | B22: =B$10*B14 -> 2126576.5 | C22: =C$10*C14 -> 3487854.8 | D22: =D$10*D14 -> 1824395.3 | E22: =E$10*E14 -> 1302677.4 | F22: =F$10*F14 -> 104234.14 | G22: =SUM(B22:F22) -> 8845738.2 | H22: 18105.301 | I22: Changes in portfolio value over each semi-annual period reflect both stock-specific performance and broader market conditions. The portfolio shows periods of recovery and drawdown, consistent with overall market volatility over 2022–2025. The large fluctuations in Tata Elxsi and Trent Ltd. significantly influence total portfolio movement due to their higher volatility and growth orientation. HDFC Bank and Reliance provide stability, moderating extreme downside periods.
A23: Value at 2 January 2023 | B23: =B$10*B15 -> 2131482 | C23: =C$10*C15 -> 3527153.7 | D23: =D$10*D15 -> 1825011.5 | E23: =E$10*E15 -> 1316324.5 | F23: =F$10*F15 -> 103524.52 | G23: =SUM(B23:F23) -> 8903496.2 | H23: 18197.449
A24: Value at 29 December 2023 | B24: =B$10*B16 -> 2984586.6 | C24: =C$10*C16 -> 3848375.2 | D24: =D$10*D16 -> 1937234.6 | E24: =E$10*E16 -> 1368042 | F24: =F$10*F16 -> 235984.95 | G24: =SUM(B24:F24) -> 10374223 | H24: 21731.4
A25: Value at 1 January 2024 | B25: =B$10*B17 -> 2981432.6 | C25: =C$10*C17 -> 3856265.9 | D25: =D$10*D17 -> 1924597.4 | E25: =E$10*E17 -> 1375534.5 | F25: =F$10*F17 -> 231902.48 | G25: =SUM(B25:F25) -> 10369733 | H25: 21741.9
A26: Value at 31 December 2024 | B26: =B$10*B18 -> 2339949.8 | C26: =C$10*C18 -> 3631314.2 | D26: =D$10*D18 -> 2036756 | E26: =E$10*E18 -> 1719649.8 | F26: =F$10*F18 -> 550633.15 | G26: =SUM(B26:F26) -> 10278303 | H26: 23644.801
A27: Value at 1 January 2025 | B27: =B$10*B19 -> 2321771.7 | C27: =C$10*C19 -> 3648642.6 | D27: =D$10*D19 -> 2048129.5 | E27: =E$10*E19 -> 1721936.6 | F27: =F$10*F19 -> 546358.45 | G27: =SUM(B27:F27) -> 10286839 | H27: 23742.9
A28: Value at 28 November 2025 | B28: =B$10*B20 -> 1796084.4 | C28: =C$10*C20 -> 4701813.2 | D28: =D$10*D20 -> 2346476.3 | E28: =E$10*E20 -> 1469267.1 | F28: =F$10*F20 -> 328839.48 | G28: =SUM(B28:F28) -> 10642480 | H28: 26202.949
A30: Returns calculated on basis of different dates
A31: Return from 1 April 2022 to 30 December 2022 (%) | B31: =(B22-B21)/B21*100 -> -29.114115 | C31: =(C22-C21)/C21*100 -> -3.7780429 | D31: =(D22-D21)/D21*100 -> 9.3678907 | E31: =(E22-E21)/E21*100 -> -19.054959 | F31: =(F22-F21)/F21*100 -> 6.6487001 | G31: =(G22-G21)/G21*100 -> -11.542618 | H31: =(H14-H13)/H13*100 -> 2.460897 | I31: In the period from April 2022 to December 2022, the portfolio delivered negative returns. This was mainly due to underperformance of Tata Elxsi, Infosys, and the tech sector, as global IT spending faced a slowdown and high-growth stocks saw major corrections, even though the overall Nifty 50 index posted a slightly positive return thanks to broader sector strength | J31: Answer for Part(a). Analysing Portfolio Performance for each year individually on basis of starting and ending price
A32: Return from 2 January 2023 to 29 December 2023 (%) | B32: =(B24-B23)/B23*100 -> 40.024011 | C32: =(C24-C23)/C23*100 -> 9.1071027 | D32: =(D24-D23)/D23*100 -> 6.1491717 | E32: =(E24-E23)/E23*100 -> 3.928934 | F32: =(F24-F23)/F23*100 -> 127.95078 | G32: =(G24-G23)/G23*100 -> 16.518535 | H32: =(H24-H23)/H23*100 -> 19.420036 | I32: In 2023, the portfolio return was positive but did not outperform the Nifty 50 index. The summary table shows a portfolio return of 16.52%, while the Nifty 50 delivered a higher return of approximately 19.42% during the same period. This means the portfolio underperformed the benchmark in that year, despite positive contributions from stocks such as Reliance Industries and Trent Ltd.
A33: Return from 1 January 2024 to 31 December 2024(%) | B33: =(B26-B25)/B25*100 -> -21.515925 | C33: =(C26-C25)/C25*100 -> -5.8334089 | D33: =(D26-D25)/D25*100 -> 5.8276374 | E33: =(E26-E25)/E25*100 -> 25.016843 | F33: =(F26-F25)/F25*100 -> 137.44169 | G33: =(G26-G25)/G25*100 -> -0.88170095 | H33: =(H26-H25)/H25*100 -> 8.7522266 | I33: In 2024, the portfolio posted a small negative return, underperforming the Nifty 50, which remained positive. The drag was again due to IT stocks such as Tata Elxsi and Infosys struggling with weak global demand and higher valuations, and Trent Ltd facing valuation corrections after strong prior years, whereas the Nifty index benefited from broad-based gains in financial, energy, and core sector stocks
A34: Return from 1 January 2025 to 28 November 2025(%) | B34: =(B28-B27)/B27*100 -> -22.641643 | C34: =(C28-C27)/C27*100 -> 28.864724 | D34: =(D28-D27)/D27*100 -> 14.566793 | E34: =(E28-E27)/E27*100 -> -14.673567 | F34: =(F28-F27)/F27*100 -> -39.812503 | G34: =(G28-G27)/G27*100 -> 3.4572491 | H34: =(H28-H27)/H27*100 -> 10.361198 | I34: By 2025 year-to-date (till late November), the portfolio generated modest positive returns but lagged behind the Nifty 50, which continued to rise on the back of strong corporate earnings, index heavyweights like Reliance Industries, and broad market optimism. Some concentrated holdings in the portfolio did not keep pace with market leaders despite positive news flow and continued operational growth in large caps.
A36: Returns and Volatilty on the basis of stock price data from 1 April 2022 to 28 November 2025
A37: Average Annualized Return over 3 years(%) | B37: ='Stock Price from 1 April 2022 t'!F911 -> -9.2465164 | C37: ='Stock Price from 1 April 2022 t'!M911 -> 10.09232 | D37: ='Stock Price from 1 April 2022 t'!T911 -> 12.20683 | E37: ='Stock Price from 1 April 2022 t'!AA911 -> 0.51480372 | F37: ='Stock Price from 1 April 2022 t'!AH911 -> 48.880525 | G37: ='Stock Price from 1 April 2022 t'!AJ911 -> 3.013674 | H37: ='Stock Price from 1 April 2022 t'!AS911 -> 12.131737 | I37: The portfolio’s annualized return is about 3.01%, which is clearly below the Nifty 50’s 12.57%, indicating that over 1 April 2022–28 November 2025 the five‑stock allocation has generated positive but substantially lower growth than the broad market index. This gap arises because large negative or low returns from Tata Elxsi, Infosys and Trent have diluted the strong performance from Reliance Industries and HDFC Bank during this period. | J37: Calculation is done in Stock Price from 1 April 2022 to 28 November 2025 Sheet in the end.
A38: Average Annualized Standard Deviation over 3 years(%) | B38: ='Stock Price from 1 April 2022 t'!F912 -> 30.596816 | C38: ='Stock Price from 1 April 2022 t'!M912 -> 21.537311 | D38: ='Stock Price from 1 April 2022 t'!T912 -> 20.028049 | E38: ='Stock Price from 1 April 2022 t'!AA912 -> 24.813128 | F38: ='Stock Price from 1 April 2022 t'!AH912 -> 34.568797 | G38: ='Stock Price from 1 April 2022 t'!AJ912 -> 16.726028 | H38: ='Stock Price from 1 April 2022 t'!AS912 -> 12.901207 | I38: Portfolio volatility is around 16.72%, moderately higher than the Nifty 50’s 12.92%, showing that the portfolio took more risk than the index while delivering lower return. The higher risk is consistent with exposure to volatile IT and retail stocks such as Tata Elxsi, Infosys and Trent, whose prices have swung sharply with changes in global tech demand and domestic consumption themes. | J38: Calculation is done in Stock Price from 1 April 2022 to 28 November 2025 Sheet in the end.
A39: Average Annualised Return from 1 April 2022 to 30 December 2022(%) | B39: =((AVERAGE('Stock Price from 1 April 2022 t'!F6:F191)+1)^252-1)*100 -> -31.950347 | C39: =((AVERAGE('Stock Price from 1 April 2022 t'!M6:M191)+1)^252-1)*100 -> -1.8390761 | D39: =((AVERAGE('Stock Price from 1 April 2022 t'!T6:T191)+1)^252-1)*100 -> 16.349158 | E39: =((AVERAGE('Stock Price from 1 April 2022 t'!AA6:AA191)+1)^252-1)*100 -> -21.947327 | F39: =((AVERAGE('Stock Price from 1 April 2022 t'!AH6:AH191)+1)^252-1)*100 -> 15.173566 | G39: =((AVERAGE('Stock Price from 1 April 2022 t'!AJ6:AJ191)+1)^252-1)*100 -> -12.660312 | H39: =((AVERAGE('Stock Price from 1 April 2022 t'!AS6:AS191)+1)^252-1)*100 -> 4.6003416 | I39: The portfolio delivered a negative annualized return (−12.7%) in 2022, whereas Nifty 50 was slightly positive (about 4.6%), indicating clear underperformance in the first year. Losses stem largely from weak performance of Tata Elxsi and Infosys during the global tech correction, which outweighed relatively better resilience in Reliance and HDFC Bank.
A40: Average Annualised Return from 2 January 2023 to 29 December 2023 (%) | B40: =((AVERAGE('Stock Price from 1 April 2022 t'!F192:F436)+1)^252-1)*100 -> 44.68629 | C40: =((AVERAGE('Stock Price from 1 April 2022 t'!M192:M436)+1)^252-1)*100 -> 12.414669 | D40: =((AVERAGE('Stock Price from 1 April 2022 t'!T192:T436)+1)^252-1)*100 -> 7.9406412 | E40: =((AVERAGE('Stock Price from 1 April 2022 t'!AA192:AA436)+1)^252-1)*100 -> 8.09614 | F40: =((AVERAGE('Stock Price from 1 April 2022 t'!AH192:AH436)+1)^252-1)*100 -> 139.13309 | G40: =((AVERAGE('Stock Price from 1 April 2022 t'!AJ192:AJ436)+1)^252-1)*100 -> 20.571753 | H40: =((AVERAGE('Stock Price from 1 April 2022 t'!AS192:AS436)+1)^252-1)*100 -> 21.224625 | I40: In 2023 the portfolio rebounded to a strong positive annualized return (20.6%) but still slightly lagged Nifty 50’s ~21.2%, meaning stock selection almost but not fully matched the broad market rally. Gains were driven by Reliance, HDFC Bank and especially Trent, which benefited from India’s consumption recovery, while Tata Elxsi’s volatility kept overall returns from surpassing the index.​​
A41: Average Annualised Return from 1 January 2024 to 31 December 2024(%) | B41: =((AVERAGE('Stock Price from 1 April 2022 t'!F437:F682)+1)^252-1)*100 -> -18.155404 | C41: =((AVERAGE('Stock Price from 1 April 2022 t'!M437:M682)+1)^252-1)*100 -> -3.244937 | D41: =((AVERAGE('Stock Price from 1 April 2022 t'!T437:T682)+1)^252-1)*100 -> 7.9181746 | E41: =((AVERAGE('Stock Price from 1 April 2022 t'!AA437:AA682)+1)^252-1)*100 -> 29.687633 | F41: =((AVERAGE('Stock Price from 1 April 2022 t'!AH437:AH682)+1)^252-1)*100 -> 155.23309 | G41: =((AVERAGE('Stock Price from 1 April 2022 t'!AJ437:AJ682)+1)^252-1)*100 -> -0.82566998 | H41: =((AVERAGE('Stock Price from 1 April 2022 t'!AS437:AS682)+1)^252-1)*100 -> 10.241484 | I41: For 2024 the portfolio return turned marginally negative (−0.83%) even as Nifty 50 remained comfortably positive (~10.2%), again signaling underperformance. This reflects another weak phase for IT and high‑beta retail names, with Infosys and Trent showing large swings that offset more stable contributions from Reliance and HDFC Bank.
A42: Average Annualised Return from 1 January 2025 to 28 November 2025(%) | B42: =((AVERAGE('Stock Price from 1 April 2022 t'!F683:F908)+1)^252-1)*100 -> -22.423989 | C42: =((AVERAGE('Stock Price from 1 April 2022 t'!M683:M908)+1)^252-1)*100 -> 36.116918 | D42: =((AVERAGE('Stock Price from 1 April 2022 t'!T683:T908)+1)^252-1)*100 -> 18.50252 | E42: =((AVERAGE('Stock Price from 1 April 2022 t'!AA683:AA908)+1)^252-1)*100 -> -13.342998 | F42: =((AVERAGE('Stock Price from 1 April 2022 t'!AH683:AH908)+1)^252-1)*100 -> -38.982072 | G42: =((AVERAGE('Stock Price from 1 April 2022 t'!AJ683:AJ908)+1)^252-1)*100 -> 3.6824764 | H42: =((AVERAGE('Stock Price from 1 April 2022 t'!AS683:AS908)+1)^252-1)*100 -> 11.147063 | I42: Year‑to‑date 2025, the portfolio has a modest positive annualized return (3.67%) but trails Nifty 50’s 11.15%, so the benchmark continues to outperform sharply. The gap suggests that recent index gains have been driven by broad‑based strength in large‑cap sectors that the five‑stock portfolio does not fully capture, while concentrated positions remain more volatile and less rewarded.
A43: Annualised Volatility from 1 April 2022 to 30 December 2022(%) | B43: =(STDEV('Stock Price from 1 April 2022 t'!F6:F191)*SQRT(252)*100) -> 40.575001 | C43: =(STDEV('Stock Price from 1 April 2022 t'!M6:M191)*SQRT(252)*100) -> 25.884746 | D43: =(STDEV('Stock Price from 1 April 2022 t'!T6:T191)*SQRT(252)*100) -> 24.619298 | E43: =(STDEV('Stock Price from 1 April 2022 t'!AA6:AA191)*SQRT(252)*100) -> 27.945643 | F43: =(STDEV('Stock Price from 1 April 2022 t'!AH6:AH191)*SQRT(252)*100) -> 32.856706 | G43: =(STDEV('Stock Price from 1 April 2022 t'!AJ6:AJ191)*SQRT(252)*100) -> 20.732813 | H43: =(STDEV('Stock Price from 1 April 2022 t'!AS6:AS191)*SQRT(252)*100) -> 15.617384 | I43: Year‑wise, volatility patterns show that 2022 was the most turbulent period, with all stocks exhibiting their highest annualized volatility, in line with post‑COVID policy tightening and tech sector corrections, while 2023 and 2024 see a gradual normalization of risk for most names and for Nifty 50. However, even in the quieter years the portfolio’s volatility remains above the index, which suggests that diversification across only five correlated stocks is not sufficient to bring risk down to market levels.
A44: Annualised Volatility from 2 January 2023 to 29 December 2023(%) | B44: =(STDEV('Stock Price from 1 April 2022 t'!F192:F436)*SQRT(252)*100) -> 20.578339 | C44: =(STDEV('Stock Price from 1 April 2022 t'!M192:M436)*SQRT(252)*100) -> 17.418985 | D44: =(STDEV('Stock Price from 1 April 2022 t'!T92:T436)*SQRT(252)*100) -> 17.798204 | E44: =(STDEV('Stock Price from 1 April 2022 t'!AA192:AA436)*SQRT(252)*100) -> 23.301968 | F44: =(STDEV('Stock Price from 1 April 2022 t'!AH192:AH436)*SQRT(252)*100) -> 25.568755 | G44: =(STDEV('Stock Price from 1 April 2022 t'!AJ192:AJ436)*SQRT(252)*100) -> 12.776116 | H44: =(STDEV('Stock Price from 1 April 2022 t'!AS192:AS436)*SQRT(252)*100) -> 9.8146235
A45: Annualised Volatility from 1 January 2023 to 29 December 2024(%) | B45: =(STDEV('Stock Price from 1 April 2022 t'!F437:F682)*SQRT(252)*100) -> 31.896066 | C45: =(STDEV('Stock Price from 1 April 2022 t'!M437:M682)*SQRT(252)*100) -> 22.906085 | D45: =(STDEV('Stock Price from 1 April 2022 t'!T437:T682)*SQRT(252)*100) -> 22.373695 | E45: =(STDEV('Stock Price from 1 April 2022 t'!AA437:AA682)*SQRT(252)*100) -> 22.873176 | F45: =(STDEV('Stock Price from 1 April 2022 t'!AH437:AH682)*SQRT(252)*100) -> 37.937782 | G45: =(STDEV('Stock Price from 1 April 2022 t'!AJ437:AJ682)*SQRT(252)*100) -> 16.752292 | H45: =(STDEV('Stock Price from 1 April 2022 t'!AS437:AS682)*SQRT(252)*100) -> 14.067891
A46: Annualised Volatility from 1 January 2025 to 28 November 2025(%) | B46: =(STDEV('Stock Price from 1 April 2022 t'!F683:F908)*SQRT(252)*100) -> 28.613759 | C46: =(STDEV('Stock Price from 1 April 2022 t'!M683:M908)*SQRT(252)*100) -> 20.132013 | D46: =(STDEV('Stock Price from 1 April 2022 t'!T683:T908)*SQRT(252)*100) -> 16.039199 | E46: =(STDEV('Stock Price from 1 April 2022 t'!AA683:AA908)*SQRT(252)*100) -> 25.721073 | F46: =(STDEV('Stock Price from 1 April 2022 t'!AH683:AH908)*SQRT(252)*100) -> 39.629754 | G46: =(STDEV('Stock Price from 1 April 2022 t'!AJ683:AJ908)*SQRT(252)*100) -> 16.836515 | H46: =(STDEV('Stock Price from 1 April 2022 t'!AS683:AS908)*SQRT(252)*100) -> 12.09571
A47: Beta for overall 3 years | B47: =_xlfn.COVARIANCE.P('Stock Price from 1 April 2022 t'!F6:F908,'Stock Price from 1 April 2022 t'!$AS$6:$AS$908)/VARP('Stock Price from 1 April 2022 t'!F6:F908,'Stock Price from 1 April 2022 t'!$AS$6:$AS$908) -> 0.26477508 | C47: =_xlfn.COVARIANCE.P('Stock Price from 1 April 2022 t'!M6:M908,'Stock Price from 1 April 2022 t'!$AS$6:$AS$908)/VARP('Stock Price from 1 April 2022 t'!M6:M908,'Stock Price from 1 April 2022 t'!$AS$6:$AS$908) -> 0.61367069 | D47: =_xlfn.COVARIANCE.P('Stock Price from 1 April 2022 t'!T6:T908,'Stock Price from 1 April 2022 t'!$AS$6:$AS$908)/VARP('Stock Price from 1 April 2022 t'!T6:T908,'Stock Price from 1 April 2022 t'!$AS$6:$AS$908) -> 0.60352434 | E47: =_xlfn.COVARIANCE.P('Stock Price from 1 April 2022 t'!AA6:AA908,'Stock Price from 1 April 2022 t'!$AS$6:$AS$908)/VARP('Stock Price from 1 April 2022 t'!AA6:AA908,'Stock Price from 1 April 2022 t'!$AS$6:$AS$908) -> 0.45969913 | F47: =_xlfn.COVARIANCE.P('Stock Price from 1 April 2022 t'!AH6:AH908,'Stock Price from 1 April 2022 t'!$AS$6:$AS$908)/VARP('Stock Price from 1 April 2022 t'!AH6:AH908,'Stock Price from 1 April 2022 t'!$AS$6:$AS$908) -> 0.27873383 | G47: =_xlfn.COVARIANCE.P('Stock Price from 1 April 2022 t'!AJ6:AJ908,'Stock Price from 1 April 2022 t'!$AS$6:$AS$908)/VARP('Stock Price from 1 April 2022 t'!AJ6:AJ908,'Stock Price from 1 April 2022 t'!$AS$6:$AS$908) -> 0.77651722 | H47: =_xlfn.COVARIANCE.P('Stock Price from 1 April 2022 t'!AS6:AS908,'Stock Price from 1 April 2022 t'!$AS$6:$AS$908)/VARP('Stock Price from 1 April 2022 t'!AS6:AS908,'Stock Price from 1 April 2022 t'!$AS$6:$AS$908) -> 1 | I47: With a beta of about 0.78, the portfolio is less sensitive to broad market movements than the index, meaning it tends to move less than Nifty 50 during large up or down days. This muted market sensitivity reflects balancing between relatively defensive heavyweights like Reliance Industries and HDFC Bank and more cyclical names in IT and retail | J47: Beta= Covariance/Variance
A48: Beta for 1 April 2022 to 30 December 2022 | G48: =_xlfn.COVARIANCE.P('Stock Price from 1 April 2022 t'!AJ6:AJ191,'Stock Price from 1 April 2022 t'!AS6:AS191)/VARP('Stock Price from 1 April 2022 t'!AJ6:AJ191) -> 0.57897471 | H48: 1 | I48: The beta values by sub‑period (around 0.58–0.88 versus Nifty’s 1) indicate that the portfolio’s sensitivity to market movements has increased over time: beta is lowest in 2022 and rises toward 0.88 in 2025 year‑to‑date. This means the portfolio behaves more like the index in recent periods, but still with higher standalone volatility, implying that stock‑specific noise and sector concentration continue to play a larger role than in a diversified benchmark.​
A49: Beta for 2 January 2023 to 29 December 2023 | G49: =_xlfn.COVARIANCE.P('Stock Price from 1 April 2022 t'!AJ192:AJ436,'Stock Price from 1 April 2022 t'!AS192:AS436)/VARP('Stock Price from 1 April 2022 t'!AJ192:AJ436) -> 0.62429082 | H49: 1
A50: Beta for 1 January 2024 to 31 December 2024 | G50: =_xlfn.COVARIANCE.P('Stock Price from 1 April 2022 t'!AJ437:AJ682,'Stock Price from 1 April 2022 t'!AS437:AS682)/VARP('Stock Price from 1 April 2022 t'!AJ437:AJ682) -> 0.66956233 | H50: 1
A51: Beta for 1 January 2025 to 28 November 2025 | G51: =_xlfn.COVARIANCE.P('Stock Price from 1 April 2022 t'!AJ683:AJ981,'Stock Price from 1 April 2022 t'!AS683:AS981)/VARP('Stock Price from 1 April 2022 t'!AJ683:AJ981) -> 0.87127503 | H51: 1
A52: Risk Free Rate(%) | B52: 6.5 | C52: 6.5 | D52: 6.5 | E52: 6.5 | F52: 6.5 | G52: 6.5 | H52: 6.5 | I52: 10-year Treasury Bill Rate on government bond
A54: Portfolio Ratio's Analysis over 3 years
A55: Sharpe Ratio from 1 April 2022 to 28 November 2025 | B55: =(B37-B52)/B38 -> -0.51464558 | C55: =(C37-C52)/C38 -> 0.16679518 | D55: =(D37-D52)/D38 -> 0.28494188 | E55: =(E37-E52)/E38 -> -0.24121087 | F55: =(F37-F52)/F38 -> 1.2259763 | G55: =(G37-G52)/G38 -> -0.20843718 | H55: =(H37-H52)/H38 -> 0.4365279 | I55: The portfolio Sharpe ratio is slightly negative (around −0.21), whereas Nifty 50’s Sharpe ratio is positive, implying that after adjusting for the 6.5% risk‑free rate, the portfolio has not been adequately compensated for the volatility taken. In practical terms, taking the same risk through the index would have produced a better excess return per unit of total risk than this concentrated set of stocks | J55: Answer for Part (a). Evaluation of portfolio using metrics like sharpe ratio, Treynor ratio, etc. Formulas Used for Sharpe Ratio=(Annual Return-Risk free rate)/Annual Volatilty, Treynor Ratio=(Annual Return-Risk free Rate/Beta), Janesen's alpha=Annual Return-(Risk free rate+Beta*(Risk Premium))
A56: Treynor Ratio from 1 April 2022 to 28 November 2025 | B56: =(B37-B52)/(100*B47) -> -0.59471293 | C56: =(C37-C52)/(100*C47) -> 0.05853823 | D56: =(D37-D52)/(100*D47) -> 0.094558402 | E56: =(E37-E52)/(100*E47) -> -0.13019812 | F56: =(F37-F52)/(100*F47) -> 1.5204658 | G56: =(G37-G52)/(100*G47) -> -0.044896957 | H56: =(H37-H52)/(100*H47) -> 0.056317367 | I56: The Treynor ratio is marginally negative (about −0.04) compared with a clearly positive Treynor for Nifty 50, showing that per unit of systematic (beta) risk the portfolio has delivered insufficient excess return. This indicates that stock selection rather than market timing is the main issue: even with lower beta, the chosen stocks have not generated returns in line with what would be expected for their level of market risk
A57: Jensen's Alpha 1 April 2022 to 28 November 2025 | B57: =B37-(B52+B47*($H$37-B52)) -> -17.23766 | C57: =C37-(C52+C47*($H$37-C52)) -> 0.13628789 | D57: =D37-(D52+D47*($H$37-D52)) -> 2.3079396 | E57: =E37-(E52+E47*($H$37-E52)) -> -8.5741007 | F57: =F37-(F52+F47*($H$37-F52)) -> 40.81077 | G57: =G37-(G52+G47*($H$37-G52)) -> -7.8594665 | H57: =H37-(H52+H47*($H$37-H52)) -> -1.5987212e-14 | I57: Jensen’s alpha of roughly −7.86% indicates that, given a beta of 0.78, the portfolio has underperformed the return predicted by CAPM by more than 8 percentage points per year versus Nifty 50. This negative alpha confirms that active choices—especially the heavy exposure to high‑volatility underperformers in IT and retail—have destroyed value relative to a simple passive investment in the benchmark index
A59: Portfolio's Ratio Analysis individually for each year
A60: Sharpe Ratio from 1 April 2022 to 30 December 2022 | G60: =(G39-G$52)/G43 -> -0.92415402 | H60: =(H39-H$52)/H43 -> -0.12163743 | I60: The portfolio Sharpe ratio is about −0.92 while Nifty 50’s is only slightly negative (−0.12), meaning that in the first year the portfolio delivered much worse risk‑adjusted performance than the index; losses from concentrated bets (especially in IT and Trent) were not compensated by the volatility taken. | J60: Answer for Part(a). Analysing Portfolio Performance for each year individually on basis of average returns and standard deviation.
A61: Sharpe Ratio from 2 January 2023 to 29 December 2023 | G61: =(G40-G$52)/G44 -> 1.1014109 | H61: =(H40-H$52)/H44 -> 1.5002741 | I61: In 2023 the portfolio Sharpe ratio turns strongly positive at 1.10 and is still below Nifty 50’s 1.50, so risk‑adjusted performance improves sharply but does not fully match the benchmark; the portfolio participates in the bull market but index constituents, on average, convert risk into return more efficiently
A62: Sharpe Ratio from 1 January 2024 to 31 December 2024 | G62: =(G41-G$52)/G45 -> -0.43729361 | H62: =(H41-H$52)/H45 -> 0.26595915 | I62: For 2024 the portfolio Sharpe ratio falls back into negative territory (−0.44) while Nifty 50 stays positive (0.27), indicating that the portfolio delivered a small or negative excess return despite non‑trivial volatility, whereas the index continued to reward risk with positive excess returns.
A63: Sharpe Ratio from 1 January 2025 to 28 November 2025 | G63: =(G42-G$52)/G46 -> -0.16734601 | H63: =(H42-H$52)/H46 -> 0.384191 | I63: Year‑to‑date 2025 the portfolio Sharpe ratio is mildly negative (−0.17) versus a positive 0.38 for Nifty 50, showing that the portfolio again lags significantly in risk‑adjusted terms, with modest returns that do not justify the volatility borne.
A64: Treynor Ratio from 1 April 2022 to 30 December 2022 | G64: =(G39-G$52)/(G48*100) -> -0.33093522 | H64: =(H39-H$52)/(H48*100) -> -0.018996584 | I64: The Treynor ratio for 2022 is −0.33 compared to a near‑zero index Treynor (−0.02), which means that per unit of market risk (beta) the portfolio destroyed much more value than the benchmark in the down year
A65: Treynor Ratio from 2 January 2023 to 29 December 2023 | G65: =(G40-G$52)/(G49*100) -> 0.22540382 | H65: =(H40-H$52)/(H49*100) -> 0.14724625 | I65: In 2023 the portfolio Treynor ratio improves to 0.23 but remains below Nifty 50’s 0.15, indicating that per unit of beta, the portfolio slightly outperformed the index on a market‑risk basis even though its total‑risk Sharpe ratio was lower; active bets were rewarded when scaled only by beta.
A66: Treynor Ratio from 1 January 2024 to 31 December 2024 | G66: =(G41-G$52)/(G50*100) -> -0.10940983 | H66: =(H41-H$52)/(H50*100) -> 0.037414844 | I66: For 2024 the portfolio Treynor ratio slips close to zero (−0.11) while Nifty 50’s remains small but positive (0.04), implying that taking market risk through this portfolio was not compensated, whereas holding the index still generated a modest reward per unit of beta
A67: Treynor Ratio from 1 January 2025 to 28 November 2025 | G67: =(G42-G$52)/(G51*100) -> -0.032337935 | H67: =(H42-H$52)/(H51*100) -> 0.04647063 | I67: In 2025 YTD the Treynor ratio is slightly negative (−0.03) versus a positive 0.05 for Nifty 50, again showing that the portfolio’s exposure to systematic risk has not been properly rewarded compared to the benchmark’s broad‑based rally
A68: Jansen's alpha from 1 April 2022 to 30 December 2022 | G68: =(G39-(G$52+G48*(H39-G$52))) -> -18.060458 | H68: 0 | I68: The portfolio’s Jensen’s alpha in 2022 is −18.06%, a very large negative value, which means that after adjusting for beta and the risk‑free rate, realized return was far below what CAPM would predict given market movements; stock selection destroyed substantial value relative to Nifty 50.
A69: Jansen's alpha from 2 January 2023 to 29 December 2023 | G69: =(G40-(G$52+G49*(H40-G$52))) -> 4.8793048 | H69: 0 | I69: In 2023 Jensen’s alpha turns positive at about 4.88%, indicating that, for that year, the portfolio actually outperformed the CAPM‑implied return given its beta, even though its Sharpe ratio was below the index; active picks added value on a risk‑adjusted basis when judged against the model
A70: Jansen's alpha from 1 January 2024 to 31 December 2024 | G70: =(G41-(G$52+G50*(H41-G$52))) -> -9.830827 | H70: 0 | I70: For 2024 alpha becomes sharply negative again (−9.83%), showing significant underperformance versus the required return implied by Nifty 50 and the portfolio’s beta, driven by weak IT and retail performance despite a rising broader market.
A71: Jansen's alpha from 1 January 2025 to 28 November 2025 | G71: =(G42-(G$52+G51*(H42-G$52))) -> -6.8663935 | H71: 0 | I71: Year‑to‑date 2025 alpha is −6.87%, meaning that even in the latest period the portfolio has failed to earn its CAPM‑required return; the concentrated five‑stock allocation continues to lag the index on a risk‑adjusted basis, reinforcing that a passive Nifty 50 investment would have been superior.
A73: Individual Stock vs Diversified Portfolio Analysis using Risk and Reward Pattern
A74: Overall Return (%) | B74: =(B28-B21)/B21*100 -> -40.13052 | C74: =(C28-C21)/C21*100 -> 29.712301 | D74: =(D28-D21)/D21*100 -> 40.665328 | E74: =(E28-E21)/E21*100 -> -8.7035041 | F74: =(F28-F21)/F21*100 -> 236.45697 | G74: =(G28-G21)/G21*100 -> 6.424805 | H74: =(H28-H21)/H21*100 -> 48.286831 | I74: The portfolio’s overall return is significantly higher and more stable than Tata Elxsi’s standalone return. Tata Elxsi shows a large negative return due to its high volatility and heavy correction in the IT sector during 2022–23, whereas the diversified portfolio absorbs this shock through the strong performance of Reliance, HDFC Bank, and Trent in the later periods. This shows that the primary stock exhibits a more unpredictable and risk-heavy pattern compared to the broader portfolio. The deviation also occurs because Tata Elxsi is highly sensitive to sector cycles and investor sentiment, while the portfolio spreads exposure across BFSI, Energy, Retail, and IT, reducing dependence on a single sector. The positive results from low-beta stocks like Reliance and HDFC Bank help offset the losses from high-beta components in downturns. Therefore, the portfolio exhibits better risk-adjusted performance and lower drawdowns than the primary stock. Overall, diversification clearly provides benefits by smoothing returns, reducing portfolio volatility, and preventing deep losses during market corrections—something the individual stock fails to offer. This confirms that the multi-sector portfolio is more resilient and efficient compared to relying on Tata Elxsi alone. | J74: Answer of Part B
A75: Risk Involved over 3 years(%) | B75: 30.579877 | C75: 21.525392 | D75: 20.01697 | E75: 24.799385 | F75: 34.549751 | G75: 16.716765 | H75: 12.915369
A77: Exclusive Comparison of Tata Elxsi vs Portfolio Returns
A78: Parameter | B78: Tata Elxsi | C78: Portfolio | D78: Parameter | E78: Tata Elxsi | F78: Portfolio | G78: Combined Inference
A79: Overall Return (%) | B79: -40.13052 | C79: 6.424805 | D79: Annualised Volatility from 1 April 2022 to 30 December 2022(%) | E79: 40.575001 | F79: 20.732813 | G79: Over the three-year evaluation period, Tata Elxsi as a standalone investment showed a highly volatile and unpredictable performance, with an overall return of about −40% and average annualized risk (standard deviation) above 30%—significantly higher than the diversified multi-stock portfolio, which delivered a positive 6.4% overall return with a much lower 16.7% risk. The risk-reward pattern for Tata Elxsi is unfavorable: its negative annualized returns across most periods and much larger drawdowns reflect its sensitivity to global IT cycles, sector-specific corrections, and sentiment shocks—exemplified by a deep loss in 2022 driven by global tech selloffs, a sharp rebound in 2023, and renewed weakness in 2024–2025 tied to sluggish IT spending and valuation contraction, even though the company itself remained fundamentally strong and debt-free with high ROE in some years. In contrast, the diversified portfolio, by combining Tata Elxsi with Reliance Industries, HDFC Bank, Infosys, and Trent, smooths out sector and stock-specific risk, consistently showing much lower volatility each year and avoiding the extreme up-and-down swings of the single stock. Risk-adjusted metrics (Sharpe, Treynor, Jensen's alpha) paint the same picture: Tata Elxsi posts more negative values for all of these across the cycle, while the portfolio stays closer to market risk-reward balance, and its beta (systematic risk) is higher, meaning more of its risk is market-driven and less is idiosyncratic compared to the single stock. This clear pattern confirms that diversification provides substantial benefits—reducing both overall and per-period volatility, raising long-run returns, improving risk-adjusted performance, and protecting against sharp losses—so the multi-stock portfolio is much more efficient and resilient than investing in Tata Elxsi alone | J79: Final detailed answer for Part(B)
A80: Risk Involved over 3 years(%) | B80: 30.579877 | C80: 16.716765 | D80: Annualised Volatility from 2 January 2023 to 29 December 2023(%) | E80: 20.578339 | F80: 12.776116
A81: Average Annualized Return over 3 years(%) | B81: -9.2367737 | C81: 3.0102908 | D81: Annualised Volatility from 1 January 2023 to 29 December 2024(%) | E81: 31.896066 | F81: 16.752292
A82: Average Annualized Standard Deviation over 3 years(%) | B82: 30.579877 | C82: 16.716765 | D82: Annualised Volatility from 1 January 2025 to 28 November 2025(%) | E82: 28.550581 | F82: 16.799231
A83: Average Annualised Return from 1 April 2022 to 30 December 2022(%) | B83: -31.950347 | C83: -12.660312 | D83: Sharpe Ratio from 1 April 2022 to 28 November 2025 | E83: -0.51461207 | F83: -0.20875505
A84: Average Annualised Return from 2 January 2023 to 29 December 2023 (%) | B84: 44.68629 | C84: 20.571753 | D84: Treynor Ratio from 1 April 2022 to 28 November 2025 | E84: -0.59459824 | F84: =(F65-F80)/(100*F75) -> -0.0036978894
A85: Average Annualised Return from 1 January 2024 to 31 December 2024(%) | B85: -18.155404 | C85: -0.82566998 | D85: Jensen's Alpha 1 April 2022 to 28 November 2025 | E85: -17.343652 | F85: =F65-(F80+F75*($H$37-F80)) -> 9.4870203
A86: Average Annualised Return from 1 January 2025 to 28 November 2025(%) | B86: -22.337124 | C86: 3.6659615 | D86: Beta for overall 3 years | E86: 0.2646623 | F86: 0.77551594
A90: Correlation Matrix | B90: Tata Elxsi | C90: Reliance Industries | D90: HDFC Bank | E90: Infosys | F90: Trent Ltd.
A91: Tata Elxsi | B91: =CORREL('Stock Price from 1 April 2022 t'!$F$6:$F$908,'Stock Price from 1 April 2022 t'!F$6:F$908) -> 1 | C91: =CORREL('Stock Price from 1 April 2022 t'!$F$6:$F$908,'Stock Price from 1 April 2022 t'!M$6:M$908) -> 0.2210563 | D91: =CORREL('Stock Price from 1 April 2022 t'!$F$6:$F$908,'Stock Price from 1 April 2022 t'!T$6:T$908) -> 0.19755931 | E91: =CORREL('Stock Price from 1 April 2022 t'!$F$6:$F$908,'Stock Price from 1 April 2022 t'!AA$6:AA$908) -> 0.26302288 | F91: =CORREL('Stock Price from 1 April 2022 t'!$F$6:$F$908,'Stock Price from 1 April 2022 t'!AH$6:AH$908) -> 0.22454656
A92: Reliance Industries | B92: =CORREL('Stock Price from 1 April 2022 t'!$M$6:$M$908,'Stock Price from 1 April 2022 t'!F$6:F$908) -> 0.2210563 | C92: =CORREL('Stock Price from 1 April 2022 t'!$M$6:$M$908,'Stock Price from 1 April 2022 t'!M$6:M$908) -> 1 | D92: =CORREL('Stock Price from 1 April 2022 t'!$M$6:$M$908,'Stock Price from 1 April 2022 t'!T$6:T$908) -> 0.33888844 | E92: =CORREL('Stock Price from 1 April 2022 t'!$M$6:$M$908,'Stock Price from 1 April 2022 t'!AA$6:AA$908) -> 0.25538999 | F92: =CORREL('Stock Price from 1 April 2022 t'!$M$6:$M$908,'Stock Price from 1 April 2022 t'!AH$6:AH$908) -> 0.29386802
A93: HDFC Bank | B93: =CORREL('Stock Price from 1 April 2022 t'!$T$6:$T$908,'Stock Price from 1 April 2022 t'!F$6:F$908) -> 0.19755931 | C93: =CORREL('Stock Price from 1 April 2022 t'!$T$6:$T$908,'Stock Price from 1 April 2022 t'!M$6:M$908) -> 0.33888844 | D93: =CORREL('Stock Price from 1 April 2022 t'!$T$6:$T$908,'Stock Price from 1 April 2022 t'!T$6:T$908) -> 1 | E93: =CORREL('Stock Price from 1 April 2022 t'!$T$6:$T$908,'Stock Price from 1 April 2022 t'!AA$6:AA$908) -> 0.25556499 | F93: =CORREL('Stock Price from 1 April 2022 t'!$T$6:$T$908,'Stock Price from 1 April 2022 t'!AH$6:AH$908) -> 0.17934666
A94: Infosys | B94: =CORREL('Stock Price from 1 April 2022 t'!$AA$6:$AA$908,'Stock Price from 1 April 2022 t'!F$6:F$908) -> 0.26302288 | C94: =CORREL('Stock Price from 1 April 2022 t'!$AA$6:$AA$908,'Stock Price from 1 April 2022 t'!M$6:M$908) -> 0.25538999 | D94: =CORREL('Stock Price from 1 April 2022 t'!$AA$6:$AA$908,'Stock Price from 1 April 2022 t'!T$6:T$908) -> 0.25556499 | E94: =CORREL('Stock Price from 1 April 2022 t'!$AA$6:$AA$908,'Stock Price from 1 April 2022 t'!AA$6:AA$908) -> 1 | F94: =CORREL('Stock Price from 1 April 2022 t'!$AA$6:$AA$908,'Stock Price from 1 April 2022 t'!AH$6:AH$908) -> 0.1806574
A95: Trent Ltd. | B95: =CORREL('Stock Price from 1 April 2022 t'!$AH$6:$AH$908,'Stock Price from 1 April 2022 t'!F$6:F$908) -> 0.22454656 | C95: =CORREL('Stock Price from 1 April 2022 t'!$AH$6:$AH$908,'Stock Price from 1 April 2022 t'!M$6:M$908) -> 0.29386802 | D95: =CORREL('Stock Price from 1 April 2022 t'!$AH$6:$AH$908,'Stock Price from 1 April 2022 t'!T6:T$908) -> 0.17934666 | E95: =CORREL('Stock Price from 1 April 2022 t'!$AH$6:$AH$908,'Stock Price from 1 April 2022 t'!AA$6:AA$908) -> 0.1806574 | F95: =CORREL('Stock Price from 1 April 2022 t'!$AH$6:$AH$908,'Stock Price from 1 April 2022 t'!AH$6:AH$908) -> 1
A97: Covariance Matrix(Annualised) | B97: Tata Elxsi | C97: Reliance Industries | D97: HDFC Bank | E97: Infosys | F97: Trent Ltd. | H97: Inverse Covariance Matrix
A98: Tata Elxsi | B98: =B38^2/10000 -> 0.093616518 | C98: =$B$38*C38*C91/10000 -> 0.014567016 | D98: =$B$38*D38*D91/10000 -> 0.012106327 | E98: =$B$38*E38*E91/10000 -> 0.019968769 | F98: =$B$38*F38*F91/10000 -> 0.02375018 | H98: {=MINVERSE(B98:F102)} -> 12.164965 | I98: -1.7277113 | J98: -1.6635081 | K98: -2.8261824 | L98: -1.5620814
A99: Reliance Industries | B99: =B38*$C$38*B92/10000 -> 0.014567016 | C99: =C38*$C$38*C92/10000 -> 0.046385577 | D99: =D38*$C$38*D92/10000 -> 0.014617964 | E99: =E38*$C$38*E92/10000 -> 0.013648247 | F99: =F38*$C$38*F92/10000 -> 0.02187903 | H99: -1.7277113 | I99: 26.902467 | J99: -7.2563923 | K99: -3.0421596 | L99: -3.4336554
A100: HDFC Bank | B100: =B38*$D$38*B93/10000 -> 0.012106327 | C100: =C38*$D$38*C93/10000 -> 0.014617964 | D100: =D38*$D$38*D93/10000 -> 0.040112274 | E100: =E38*$D$38*E93/10000 -> 0.01270052 | F100: =F38*$D$38*F93/10000 -> 0.012416986 | H100: -1.6635081 | I100: -7.2563923 | J100: 29.539205 | K100: -3.7115002 | L100: -0.9288923
A101: Infosys | B101: =B38*$E$38*B94/10000 -> 0.019968769 | C101: =C38*$E$38*C94/10000 -> 0.013648247 | D101: =D38*$E$38*D94/10000 -> 0.01270052 | E101: =E38*$E$38*E94/10000 -> 0.061569133 | F101: =F38*$E$38*F94/10000 -> 0.015496069 | H101: -2.8261824 | I101: -3.0421596 | J101: -3.7115002 | K101: 18.834588 | L101: -0.93802871
A102: Trent Ltd. | B102: =B38*$F$38*B95/10000 -> 0.02375018 | C102: =C38*$F$38*C95/10000 -> 0.02187903 | D102: =D38*$F$38*D95/10000 -> 0.012416986 | E102: =E38*$F$38*E95/10000 -> 0.015496069 | F102: =F38*$F$38*F95/10000 -> 0.11950017 | H102: -1.5620814 | I102: -3.4336554 | J102: -0.9288923 | K102: -0.93802871 | L102: 9.5254639
A105: Portfolio that Mimics NIFTY 50: Same sharp ratio
A106: Companies | B106: Tata Elxsi | C106: Reliance Industries | D106: HDFC Bank | E106: Infosys | F106: Trent Ltd. | G106: Total | H106: Index Sharpe Ratio
A107: Weights(%) | B107: 0.18 | C107: 0.313 | D107: 0.155 | E107: 0.1 | F107: 0.252 | G107: =SUM(B107:F107) -> 1
A108: Average Annual Return (%) | G108: ='Stock Price from 1 April 2022 t'!AK911 -> 14.035942 | H108: =H37 -> 12.131737
A109: Average Standard Deviation(%) | G109: ='Stock Price from 1 April 2022 t'!AK912 -> 17.264137 | H109: =H38 -> 12.901207
A110: Risk Free Rate(%) | G110: 6.5 | H110: 6.5
A111: Sharpe Ratio | G111: =(G108-G110)/G109 -> 0.43650848 | H111: =H55 -> 0.4365279
A118: Minimum Variance
A119: Company | B119: Tata Elxsi | C119: Reliance Industries | D119: HDFC | E119: Infosys | F119: Trent
...

Sheet Stock Price from 1 April 2022 t
A2: Price | B2: Open | C2: Close | D2: Adjusted Close | E2: Volume | F2: Daily Return | H2: Price | I2: Open | J2: Close | K2: Adjusted Close | L2: Volume | M2: Daily Return | O2: Price | P2: Open | Q2: Close | R2: Adjusted Close | S2: Volume | T2: Daily Return | V2: Price | W2: Open | X2: Close | Y2: Adjusted Close | Z2: Volume | AA2: Daily Return | AC2: Price | AD2: Open | AE2: Close | AF2: Adjusted Close | AG2: Volume | AH2: Daily Return | AJ2: Weighted average Daily Return | AK2: Weighted average Daily Return | AN2: Price | AO2: Open | AP2: Close | AQ2: Adjusted Close | AR2: Volume | AS2: Daily Return
A3: Ticker | B3: TATAELXSI.NS | C3: TATAELXSI.NS | D3: TATAELXSI.NS | E3: TATAELXSI.NS | H3: Ticker | I3: RELIANCE.NS | J3: RELIANCE.NS | K3: RELIANCE.NS | L3: RELIANCE.NS | O3: Ticker | P3: HDFCBANK.NS | Q3: HDFCBANK.NS | R3: HDFCBANK.NS | S3: HDFCBANK.NS | V3: Ticker | W3: INFY.NS | X3: INFY.NS | Y3: INFY.NS | Z3: INFY.NS | AC3: Ticker | AD3: TRENT.NS | AE3: TRENT.NS | AF3: TRENT.NS | AG3: TRENT.NS | AJ3: Original Portfolio | AK3: Mimicing Sharpe Ratio Portfolio | AL3: Minimum | AN3: Ticker | AO3: ^NSEI | AP3: ^NSEI | AQ3: ^NSEI | AR3: ^NSEI
A4: Date | H4: Date | O4: Date | V4: Date | AC4: Date | AN4: Date
A5: 44652 | B5: 8884 | C5: 8912.7998 | D5: 8616.2432 | E5: 1414522 | H5: 44652 | I5: 1216.5135 | J5: 1225.6743 | K5: 1208.4436 | L5: 7922880 | O5: 44652 | P5: 738.20001 | Q5: 753 | R5: 716.31012 | S5: 14568556 | V5: 44652 | W5: 1886.85 | X5: 1903.55 | Y5: 1708.8279 | Z5: 6171518 | AC5: 44652 | AD5: 1281 | AE5: 1268.45 | AF5: 1263.2819 | AG5: 491523 | AN5: 44652 | AO5: 17436.9 | AP5: 17670.449 | AQ5: 17670.449 | AR5: 291800
A6: 44655 | B6: 8988 | C6: 9009.7002 | D6: 8709.9199 | E6: 511585 | F6: 0.0109 | H6: 44655 | I6: 1225.4897 | J6: 1229.2971 | K6: 1212.0156 | L6: 7929162 | M6: 0.003 | O6: 44655 | P6: 790 | Q6: 828.40002 | R6: 788.03632 | S6: 97450970 | T6: 0.1001 | V6: 44655 | W6: 1889.75 | X6: 1882.95 | Y6: 1690.335 | Z6: 7364074 | AA6: -0.0108 | AC6: 44655 | AD6: 1256.35 | AE6: 1294.65 | AF6: 1289.3751 | AG6: 762394 | AH6: 0.0207 | AJ6: =(F6*'Part 3 Portfolio Analysis'!$B$8+M6*'Part 3 Portfolio Analysis'!$C$8+T6*'Part 3 Portfolio Analysis'!$D$8+AA6*'Part 3 Portfolio Analysis'!$E$8+AH6*'Part 3 Portfolio Analysis'!$F$8)/100 -> 0.019519623 | AK6: ='Part 3 Portfolio Analysis'!$B$107*F6+M6*'Part 3 Portfolio Analysis'!$C$107+T6*'Part 3 Portfolio Analysis'!$D$107+AA6*'Part 3 Portfolio Analysis'!$E$107+AH6*'Part 3 Portfolio Analysis'!$F$107 -> 0.0225529 | AL6: =F6*'Part 3 Portfolio Analysis'!$B$121+M6*'Part 3 Portfolio Analysis'!$C$121+'Part 3 Portfolio Analysis'!$D$121*T6+AA6*'Part 3 Portfolio Analysis'!$E$121+'Part 3 Portfolio Analysis'!$F$121*AH6 -> 0.02776432 | AN6: 44655 | AO6: 17809.1 | AP6: 18053.4 | AQ6: 18053.4 | AR6: 345500 | AS6: 0.0217
A7: 44656 | B7: 9090 | C7: 8878.3496 | D7: 8582.9414 | E7: 617070 | F7: -0.0146 | H7: 44656 | I7: 1223.4822 | J7: 1211.9216 | K7: 1194.8843 | L7: 13149870 | M7: -0.0141 | O7: 44656 | P7: 833.34998 | Q7: 804.125 | R7: 764.94397 | S7: 30922582 | T7: -0.0293 | V7: 44656 | W7: 1883.8 | X7: 1861.1 | Y7: 1670.7203 | Z7: 5472024 | AA7: -0.0116 | AC7: 44656 | AD7: 1310 | AE7: 1319.2 | AF7: 1313.8251 | AG7: 1337792 | AH7: 0.019 | AJ7: =(F7*'Part 3 Portfolio Analysis'!$B$8+M7*'Part 3 Portfolio Analysis'!$C$8+T7*'Part 3 Portfolio Analysis'!$D$8+AA7*'Part 3 Portfolio Analysis'!$E$8+AH7*'Part 3 Portfolio Analysis'!$F$8)/100 -> -0.016059713 | AK7: ='Part 3 Portfolio Analysis'!$B$107*F7+M7*'Part 3 Portfolio Analysis'!$C$107+T7*'Part 3 Portfolio Analysis'!$D$107+AA7*'Part 3 Portfolio Analysis'!$E$107+AH7*'Part 3 Portfolio Analysis'!$F$107 -> -0.0079548 | AL7: =F7*'Part 3 Portfolio Analysis'!$B$121+M7*'Part 3 Portfolio Analysis'!$C$121+'Part 3 Portfolio Analysis'!$D$121*T7+AA7*'Part 3 Portfolio Analysis'!$E$121+'Part 3 Portfolio Analysis'!$F$121*AH7 -> -0.01690828 | AN7: 44656 | AO7: 18080.6 | AP7: 17957.4 | AQ7: 17957.4 | AR7: 283500 | AS7: -0.0053
A8: 44657 | B8: 8875 | C8: 8893.6504 | D8: 8597.7324 | E8: 372750 | F8: 0.0017 | H8: 44657 | I8: 1193.9463 | J8: 1208.6912 | K8: 1191.6993 | L8: 12257215 | M8: -0.0027 | O8: 44657 | P8: 793.84998 | Q8: 775.42499 | R8: 737.64239 | S8: 27027860 | T8: -0.0357 | V8: 44657 | W8: 1855 | X8: 1828.85 | Y8: 1641.769 | Z8: 5407453 | AA8: -0.0173 | AC8: 44657 | AD8: 1323.55 | AE8: 1328.3 | AF8: 1322.8882 | AG8: 907711 | AH8: 0.0069 | AJ8: =(F8*'Part 3 Portfolio Analysis'!$B$8+M8*'Part 3 Portfolio Analysis'!$C$8+T8*'Part 3 Portfolio Analysis'!$D$8+AA8*'Part 3 Portfolio Analysis'!$E$8+AH8*'Part 3 Portfolio Analysis'!$F$8)/100 -> -0.0091406227 | AK8: ='Part 3 Portfolio Analysis'!$B$107*F8+M8*'Part 3 Portfolio Analysis'!$C$107+T8*'Part 3 Portfolio Analysis'!$D$107+AA8*'Part 3 Portfolio Analysis'!$E$107+AH8*'Part 3 Portfolio Analysis'!$F$107 -> -0.0060638 | AL8: =F8*'Part 3 Portfolio Analysis'!$B$121+M8*'Part 3 Portfolio Analysis'!$C$121+'Part 3 Portfolio Analysis'!$D$121*T8+AA8*'Part 3 Portfolio Analysis'!$E$121+'Part 3 Portfolio Analysis'!$F$121*AH8 -> -0.0139828 | AN8: 44657 | AO8: 17842.75 | AP8: 17807.65 | AQ8: 17807.65 | AR8: 328800 | AS8: -0.0083
A9: 44658 | B9: 8907 | C9: 8747.7998 | D9: 8456.7334 | E9: 343816 | F9: -0.0164 | H9: 44658 | I9: 1197.6382 | J9: 1187.3699 | K9: 1170.6776 | L9: 15496499 | M9: -0.0176 | O9: 44658 | P9: 770.65002 | Q9: 758.375 | R9: 721.42322 | S9: 40781732 | T9: -0.022 | V9: 44658 | W9: 1821.05 | X9: 1811 | Y9: 1625.7451 | Z9: 5797544 | AA9: -0.0098 | AC9: 44658 | AD9: 1336 | AE9: 1307.75 | AF9: 1302.4219 | AG9: 1038577 | AH9: -0.0155 | AJ9: =(F9*'Part 3 Portfolio Analysis'!$B$8+M9*'Part 3 Portfolio Analysis'!$C$8+T9*'Part 3 Portfolio Analysis'!$D$8+AA9*'Part 3 Portfolio Analysis'!$E$8+AH9*'Part 3 Portfolio Analysis'!$F$8)/100 -> -0.016698169 | AK9: ='Part 3 Portfolio Analysis'!$B$107*F9+M9*'Part 3 Portfolio Analysis'!$C$107+T9*'Part 3 Portfolio Analysis'!$D$107+AA9*'Part 3 Portfolio Analysis'!$E$107+AH9*'Part 3 Portfolio Analysis'!$F$107 -> -0.0167568 | AL9: =F9*'Part 3 Portfolio Analysis'!$B$121+M9*'Part 3 Portfolio Analysis'!$C$121+'Part 3 Portfolio Analysis'!$D$121*T9+AA9*'Part 3 Portfolio Analysis'!$E$121+'Part 3 Portfolio Analysis'!$F$121*AH9 -> -0.01708314 | AN9: 44658 | AO9: 17723.301 | AP9: 17639.551 | AQ9: 17639.551 | AR9: 308800 | AS9: -0.0094
A10: 44659 | B10: 8791.5498 | C10: 8685.2002 | D10: 8396.2168 | E10: 778818 | F10: -0.0072 | H10: 44659 | I10: 1181.4396 | J10: 1207.1221 | K10: 1190.1523 | L10: 15152495 | M10: 0.0166 | O10: 44659 | P10: 756.04999 | Q10: 757.32501 | R10: 720.42438 | S10: 41256322 | T10: -0.0014 | V10: 44659 | W10: 1823 | X10: 1814.6 | Y10: 1628.9768 | Z10: 5131446 | AA10: 0.002 | AC10: 44659 | AD10: 1308.2 | AE10: 1269.65 | AF10: 1264.4771 | AG10: 874307 | AH10: -0.0291 | AJ10: =(F10*'Part 3 Portfolio Analysis'!$B$8+M10*'Part 3 Portfolio Analysis'!$C$8+T10*'Part 3 Portfolio Analysis'!$D$8+AA10*'Part 3 Portfolio Analysis'!$E$8+AH10*'Part 3 Portfolio Analysis'!$F$8)/100 -> 0.0036610879 | AK10: ='Part 3 Portfolio Analysis'!$B$107*F10+M10*'Part 3 Portfolio Analysis'!$C$107+T10*'Part 3 Portfolio Analysis'!$D$107+AA10*'Part 3 Portfolio Analysis'!$E$107+AH10*'Part 3 Portfolio Analysis'!$F$107 -> -0.0034504 | AL10: =F10*'Part 3 Portfolio Analysis'!$B$121+M10*'Part 3 Portfolio Analysis'!$C$121+'Part 3 Portfolio Analysis'!$D$121*T10+AA10*'Part 3 Portfolio Analysis'!$E$121+'Part 3 Portfolio Analysis'!$F$121*AH10 -> 0.0056303 | AN10: 44659 | AO10: 17698.15 | AP10: 17784.35 | AQ10: 17784.35 | AR10: 274400 | AS10: 0.0082
A11: 44662 | B11: 8723 | C11: 8711.1504 | D11: 8421.3037 | E11: 420571 | F11: 0.003 | H11: 44662 | I11: 1199.8995 | J11: 1204.6069 | K11: 1187.6726 | L11: 9254209 | M11: -0.0021 | O11: 44662 | P11: 753 | Q11: 748.07501 | R11: 711.62512 | S11: 20799066 | T11: -0.0122 | V11: 44662 | W11: 1814 | X11: 1766.55 | Y11: 1585.842 | Z11: 8248407 | AA11: -0.0265 | AC11: 44662 | AD11: 1279.25 | AE11: 1280.9 | AF11: 1275.6813 | AG11: 509264 | AH11: 0.0089 | AJ11: =(F11*'Part 3 Portfolio Analysis'!$B$8+M11*'Part 3 Portfolio Analysis'!$C$8+T11*'Part 3 Portfolio Analysis'!$D$8+AA11*'Part 3 Portfolio Analysis'!$E$8+AH11*'Part 3 Portfolio Analysis'!$F$8)/100 -> -0.0060740778 | AK11: ='Part 3 Portfolio Analysis'!$B$107*F11+M11*'Part 3 Portfolio Analysis'!$C$107+T11*'Part 3 Portfolio Analysis'!$D$107+AA11*'Part 3 Portfolio Analysis'!$E$107+AH11*'Part 3 Portfolio Analysis'!$F$107 -> -0.0024155 | AL11: =F11*'Part 3 Portfolio Analysis'!$B$121+M11*'Part 3 Portfolio Analysis'!$C$121+'Part 3 Portfolio Analysis'!$D$121*T11+AA11*'Part 3 Portfolio Analysis'!$E$121+'Part 3 Portfolio Analysis'!$F$121*AH11 -> -0.00901978 | AN11: 44662 | AO11: 17740.9 | AP11: 17674.949 | AQ11: 17674.949 | AR11: 251700 | AS11: -0.0062
A12: 44663 | B12: 8740 | C12: 8409.25 | D12: 8129.4487 | E12: 599014 | F12: -0.0347 | H12: 44663 | I12: 1193.9 | J12: 1181.9242 | K12: 1165.3085 | L12: 13217742 | M12: -0.0188 | O12: 44663 | P12: 742 | Q12: 746.75 | R12: 710.36462 | S12: 27435402 | T12: -0.0018 | V12: 44663 | W12: 1757.5 | X12: 1742.45 | Y12: 1564.2074 | Z12: 6456184 | AA12: -0.0136 | AC12: 44663 | AD12: 1275 | AE12: 1250.5 | AF12: 1245.405 | AG12: 845636 | AH12: -0.0237 | AJ12: =(F12*'Part 3 Portfolio Analysis'!$B$8+M12*'Part 3 Portfolio Analysis'!$C$8+T12*'Part 3 Portfolio Analysis'!$D$8+AA12*'Part 3 Portfolio Analysis'!$E$8+AH12*'Part 3 Portfolio Analysis'!$F$8)/100 -> -0.01994522 | AK12: ='Part 3 Portfolio Analysis'!$B$107*F12+M12*'Part 3 Portfolio Analysis'!$C$107+T12*'Part 3 Portfolio Analysis'!$D$107+AA12*'Part 3 Portfolio Analysis'!$E$107+AH12*'Part 3 Portfolio Analysis'!$F$107 -> -0.0197418 | AL12: =F12*'Part 3 Portfolio Analysis'!$B$121+M12*'Part 3 Portfolio Analysis'!$C$121+'Part 3 Portfolio Analysis'!$D$121*T12+AA12*'Part 3 Portfolio Analysis'!$E$121+'Part 3 Portfolio Analysis'!$F$121*AH12 -> -0.01457136 | AN12: 44663 | AO12: 17584.85 | AP12: 17530.301 | AQ12: 17530.301 | AR12: 266000 | AS12: -0.0082
A13: 44664 | B13: 8470 | C13: 8383.7998 | D13: 8104.8462 | E13: 397311 | F13: -0.003 | H13: 44664 | I13: 1188.1313 | J13: 1177.5861 | K13: 1161.0314 | L13: 10354235 | M13: -0.0037 | O13: 44664 | P13: 745 | Q13: 732.47498 | R13: 696.7851 | S13: 28892520 | T13: -0.0191 | V13: 44664 | W13: 1754.95 | X13: 1748.55 | Y13: 1569.6834 | Z13: 6257693 | AA13: 0.0035 | AC13: 44664 | AD13: 1260 | AE13: 1232.8 | AF13: 1227.7771 | AG13: 742352 | AH13: -0.0142 | AJ13: =(F13*'Part 3 Portfolio Analysis'!$B$8+M13*'Part 3 Portfolio Analysis'!$C$8+T13*'Part 3 Portfolio Analysis'!$D$8+AA13*'Part 3 Portfolio Analysis'!$E$8+AH13*'Part 3 Portfolio Analysis'!$F$8)/100 -> -0.0050028166 | AK13: ='Part 3 Portfolio Analysis'!$B$107*F13+M13*'Part 3 Portfolio Analysis'!$C$107+T13*'Part 3 Portfolio Analysis'!$D$107+AA13*'Part 3 Portfolio Analysis'!$E$107+AH13*'Part 3 Portfolio Analysis'!$F$107 -> -0.007887 | AL13: =F13*'Part 3 Portfolio Analysis'!$B$121+M13*'Part 3 Portfolio Analysis'!$C$121+'Part 3 Portfolio Analysis'!$D$121*T13+AA13*'Part 3 Portfolio Analysis'!$E$121+'Part 3 Portfolio Analysis'!$F$121*AH13 -> -0.00666636 | AN13: 44664 | AO13: 17599.9 | AP13: 17475.65 | AQ13: 17475.65 | AR13: 245100 | AS13: -0.0031
A14: 44669 | B14: 8319 | C14: 7815.9502 | D14: 7555.8901 | E14: 685016 | F14: -0.0677 | H14: 44669 | I14: 1168.9791 | J14: 1173.9863 | K14: 1157.4823 | L14: 9974224 | M14: -0.0031 | O14: 44669 | P14: 709.42499 | Q14: 697.72498 | R14: 663.72833 | S14: 45620376 | T14: -0.0474 | V14: 44669 | W14: 1605.5 | X14: 1621.4 | Y14: 1455.5403 | Z14: 30523965 | AA14: -0.0727 | AC14: 44669 | AD14: 1230 | AE14: 1223.5 | AF14: 1218.515 | AG14: 395195 | AH14: -0.0075 | AJ14: =(F14*'Part 3 Portfolio Analysis'!$B$8+M14*'Part 3 Portfolio Analysis'!$C$8+T14*'Part 3 Portfolio Analysis'!$D$8+AA14*'Part 3 Portfolio Analysis'!$E$8+AH14*'Part 3 Portfolio Analysis'!$F$8)/100 -> -0.041113783 | AK14: ='Part 3 Portfolio Analysis'!$B$107*F14+M14*'Part 3 Portfolio Analysis'!$C$107+T14*'Part 3 Portfolio Analysis'!$D$107+AA14*'Part 3 Portfolio Analysis'!$E$107+AH14*'Part 3 Portfolio Analysis'!$F$107 -> -0.0296633 | AL14: =F14*'Part 3 Portfolio Analysis'!$B$121+M14*'Part 3 Portfolio Analysis'!$C$121+'Part 3 Portfolio Analysis'!$D$121*T14+AA14*'Part 3 Portfolio Analysis'!$E$121+'Part 3 Portfolio Analysis'!$F$121*AH14 -> -0.034495 | AN14: 44669 | AO14: 17183.449 | AP14: 17173.65 | AQ14: 17173.65 | AR14: 376100 | AS14: -0.0173
A15: 44670 | B15: 7944 | C15: 7693.1499 | D15: 7437.1758 | E15: 831426 | F15: -0.0157 | H15: 44670 | I15: 1180.5166 | J15: 1218.7288 | K15: 1201.5957 | L15: 26141820 | M15: 0.0381 | O15: 44670 | P15: 690.45001 | Q15: 671.09998 | R15: 638.40063 | S15: 74096022 | T15: -0.0382 | V15: 44670 | W15: 1636.65 | X15: 1562 | Y15: 1402.2163 | Z15: 17044923 | AA15: -0.0366 | AC15: 44670 | AD15: 1244.7 | AE15: 1248.45 | AF15: 1243.3634 | AG15: 1575212 | AH15: 0.0204 | AJ15: =(F15*'Part 3 Portfolio Analysis'!$B$8+M15*'Part 3 Portfolio Analysis'!$C$8+T15*'Part 3 Portfolio Analysis'!$D$8+AA15*'Part 3 Portfolio Analysis'!$E$8+AH15*'Part 3 Portfolio Analysis'!$F$8)/100 -> -0.0029625394 | AK15: ='Part 3 Portfolio Analysis'!$B$107*F15+M15*'Part 3 Portfolio Analysis'!$C$107+T15*'Part 3 Portfolio Analysis'!$D$107+AA15*'Part 3 Portfolio Analysis'!$E$107+AH15*'Part 3 Portfolio Analysis'!$F$107 -> 0.0046591 | AL15: =F15*'Part 3 Portfolio Analysis'!$B$121+M15*'Part 3 Portfolio Analysis'!$C$121+'Part 3 Portfolio Analysis'!$D$121*T15+AA15*'Part 3 Portfolio Analysis'!$E$121+'Part 3 Portfolio Analysis'!$F$121*AH15 -> -0.0024797 | AN15: 44670 | AO15: 17258.949 | AP15: 16958.65 | AQ15: 16958.65 | AR15: 401400 | AS15: -0.0125
A16: 44671 | B16: 7777.9502 | C16: 7807.7002 | D16: 7547.9146 | E16: 676897 | F16: 0.0149 | H16: 44671 | I16: 1226.2512 | J16: 1254.5642 | K16: 1236.9274 | L16: 25072240 | M16: 0.0294 | O16: 44671 | P16: 677.22498 | Q16: 677.15002 | R16: 644.15594 | S16: 49325736 | T16: 0.009 | V16: 44671 | W16: 1575 | X16: 1587.7 | Y16: 1425.2874 | Z16: 10678747 | AA16: 0.0165 | AC16: 44671 | AD16: 1251 | AE16: 1265.9 | AF16: 1260.7423 | AG16: 743805 | AH16: 0.014 | AJ16: =(F16*'Part 3 Portfolio Analysis'!$B$8+M16*'Part 3 Portfolio Analysis'!$C$8+T16*'Part 3 Portfolio Analysis'!$D$8+AA16*'Part 3 Portfolio Analysis'!$E$8+AH16*'Part 3 Portfolio Analysis'!$F$8)/100 -> 0.019420464 | AK16: ='Part 3 Portfolio Analysis'!$B$107*F16+M16*'Part 3 Portfolio Analysis'!$C$107+T16*'Part 3 Portfolio Analysis'!$D$107+AA16*'Part 3 Portfolio Analysis'!$E$107+AH16*'Part 3 Portfolio Analysis'!$F$107 -> 0.0184572 | AL16: =F16*'Part 3 Portfolio Analysis'!$B$121+M16*'Part 3 Portfolio Analysis'!$C$121+'Part 3 Portfolio Analysis'!$D$121*T16+AA16*'Part 3 Portfolio Analysis'!$E$121+'Part 3 Portfolio Analysis'!$F$121*AH16 -> 0.01967582 | AN16: 44671 | AO16: 17045.25 | AP16: 17136.551 | AQ16: 17136.551 | AR16: 286100 | AS16: 0.0105
A17: 44672 | B17: 7940 | C17: 7903.8501 | D17: 7640.8647 | E17: 1376486 | F17: 0.0123 | H17: 44672 | I17: 1269.5399 | J17: 1283.9387 | K17: 1265.8889 | L17: 21708633 | M17: 0.0234 | O17: 44672 | P17: 682.5 | Q17: 687.17499 | R17: 653.69238 | S17: 52446270 | T17: 0.0148 | V17: 44672 | W17: 1595 | X17: 1618.8 | Y17: 1453.2062 | Z17: 7766514 | AA17: 0.0196 | AC17: 44672 | AD17: 1279.85 | AE17: 1285.8 | AF17: 1280.5613 | AG17: 516906 | AH17: 0.0157 | AJ17: =(F17*'Part 3 Portfolio Analysis'!$B$8+M17*'Part 3 Portfolio Analysis'!$C$8+T17*'Part 3 Portfolio Analysis'!$D$8+AA17*'Part 3 Portfolio Analysis'!$E$8+AH17*'Part 3 Portfolio Analysis'!$F$8)/100 -> 0.017948607 | AK17: ='Part 3 Portfolio Analysis'!$B$107*F17+M17*'Part 3 Portfolio Analysis'!$C$107+T17*'Part 3 Portfolio Analysis'!$D$107+AA17*'Part 3 Portfolio Analysis'!$E$107+AH17*'Part 3 Portfolio Analysis'!$F$107 -> 0.0177486 | AL17: =F17*'Part 3 Portfolio Analysis'!$B$121+M17*'Part 3 Portfolio Analysis'!$C$121+'Part 3 Portfolio Analysis'!$D$121*T17+AA17*'Part 3 Portfolio Analysis'!$E$121+'Part 3 Portfolio Analysis'!$F$121*AH17 -> 0.01918664 | AN17: 44672 | AO17: 17234.6 | AP17: 17392.6 | AQ17: 17392.6 | AR17: 285200 | AS17: 0.0149
... A908: 45989 | B908: 5205.5 | C908: 5158.5 | D908: 5158.5 | E908: 136784 | F908: -0.0074 | H908: 45989 | I908: 1568 | J908: 1567.5 | K908: 1567.5 | L908: 8959508 | M908: 0.0026 | O908: 45989 | P908: 1007 | Q908: 1007.6 | R908: 1007.6 | S908: 15988807 | T908: -0.0019 | V908: 45989 | W908: 1565 | X908: 1560.1 | Y908: 1560.1 | Z908: 4453221 | AA908: -0.004 | AC908: 45989 | AD908: 4276.1001 | AE908: 4250.3999 | AF908: 4250.3999 | AG908: 549814 | AH908: -0.0037 | AJ908: =(F908*'Part 3 Portfolio Analysis'!$B$8+M908*'Part 3 Portfolio Analysis'!$C$8+T908*'Part 3 Portfolio Analysis'!$D$8+AA908*'Part 3 Portfolio Analysis'!$E$8+AH908*'Part 3 Portfolio Analysis'!$F$8)/100 -> -0.0022743924 | AK908: ='Part 3 Portfolio Analysis'!$B$107*F908+M908*'Part 3 Portfolio Analysis'!$C$107+T908*'Part 3 Portfolio Analysis'!$D$107+AA908*'Part 3 Portfolio Analysis'!$E$107+AH908*'Part 3 Portfolio Analysis'!$F$107 -> -0.0021451 | AL908: =F908*'Part 3 Portfolio Analysis'!$B$121+M908*'Part 3 Portfolio Analysis'!$C$121+'Part 3 Portfolio Analysis'!$D$121*T908+AA908*'Part 3 Portfolio Analysis'!$E$121+'Part 3 Portfolio Analysis'!$F$121*AH908 -> -0.00093106 | AN908: 45989 | AO908: 26237.449 | AP908: 26202.949 | AQ908: 26202.949 | AR908: 202500 | AS908: -0.0005
A909: Average Daily Return | F909: =AVERAGE(F6:F908) -> -0.00038493909 | M909: =AVERAGE(M6:M908) -> 0.00038161683 | T909: =AVERAGE(T4:T908) -> 0.00045714286 | AA909: =AVERAGE(AA6:AA908) -> 2.0376523e-05 | AH909: =AVERAGE(AH6:AH908) -> 0.0015805094 | AJ909: =AVERAGE(AJ6:AJ908) -> 0.00011783056 | AK909: =AVERAGE(AK6:AK908) -> 0.0005213402 | AL909: =AVERAGE(AL6:AL908) -> 0.00029831194 | AS909: =AVERAGE(AS4:AS908) -> 0.00045448505
A910: Daily Standard Deviation | F910: =STDEV(F6:F908) -> 0.019274183 | M910: =STDEV(M6:M908) -> 0.013567231 | T910: =STDEV(T6:T908) -> 0.012616485 | AA910: =STDEV(AA6:AA908) -> 0.015630802 | AH910: =STDEV(AH6:AH908) -> 0.021776295 | AJ910: =STDEV(AJ6:AJ908) -> 0.010536407 | AK910: =STDEV(AK6:AK908) -> 0.010875384 | AL910: =STDEV(AL6:AL908) -> 0.0098493906 | AS910: =STDEV(AS6:AS908) -> 0.0081269964
A911: Average Annual Return(%) (Assuming 252 Trading Days) | F911: =((1+F909)^252-1)*100 -> -9.2465164 | M911: =((1+M909)^252-1)*100 -> 10.09232 | T911: =((1+T909)^252-1)*100 -> 12.20683 | AA911: =((1+AA909)^252-1)*100 -> 0.51480372 | AH911: =((1+AH909)^252-1)*100 -> 48.880525 | AJ911: =((1+AJ909)^252-1)*100 -> 3.013674 | AK911: =((1+AK909)^252-1)*100 -> 14.035942 | AL911: =((1+AL909)^252-1)*100 -> 7.8060289 | AS911: =((1+AS909)^252-1)*100 -> 12.131737
A912: Average Annual Volatility(%) | F912: =F910*SQRT(252)*100 -> 30.596816 | M912: =M910*SQRT(252)*100 -> 21.537311 | T912: =T910*SQRT(252)*100 -> 20.028049 | AA912: =AA910*SQRT(252)*100 -> 24.813128 | AH912: =AH910*SQRT(252)*100 -> 34.568797 | AJ912: =AJ910*SQRT(252)*100 -> 16.726028 | AK912: =AK910*SQRT(252)*100 -> 17.264137 | AL912: =AL910*SQRT(252)*100 -> 15.635423 | AS912: =AS910*SQRT(252)*100 -> 12.901207

Sheet All References
A1: All References
B2: Link | C2: Type
A3: Part 1: Ratios & Classification | B3: =HYPERLINK("https://www.tataelxsi.com/investors","Tata Elxsi Annual Reports") -> Tata Elxsi Annual Reports | C3: Annual Reports
B4: https://www.niftyindices.com/indices/equity/sectoral-indices/nifty-it | C4: Index data
B5: https://www.screener.in/company/CNXIT/ | C5: Index data
B6: https://www.icra.in/CommonService/OpenMediaS3?Key=df4e31c8-7713-48ae-95e9-b46194039936 | C6: Rating‑agency sector report
B7: https://hr.economictimes.indiatimes.com/news/trends/indian-it-industry-expected-to-grow-3-5-revenue-in-2024-lower-than-2023-report/103151642 | C7: News / industry article
B8: https://www.ibef.org/industry/information-technology-india | C8: Govt/industry profile
B9: https://aventis-advisors.com/it-services-valuation-multiples/ | C9: Valuation study
B10: https://www.moneycontrol.com/indian-indices/nifty-it-19.html | C10: Financial portal
B11: https://ijcrt.org/papers/IJCRT2503524.pdf | C11: Academic paper
B12: https://www.allfinancejournal.com/article/view/284/7-1-14 | C12: Academic paper
A13: Part 2: Price Movement Analysis | B13: https://www.nseindia.com/get-quotes/equity?symbol=TATAELXSI
B14: https://stockpricearchive.com/tata-elxsi-share-price-history/
B15: https://dhan.co/stocks/tata-elxsi-ltd-historical-price/
B16: https://www.tataelxsi.com/news-and-events/press-releases/tata-elxsi-operating-revenue-at-rs-3729-crores-for-fy25-with-full-year-
B17: https://www.tataelxsi.com/news-and-events/press-releases/tata-elxsi-delivers-stable-revenues-in-q3-fy25
B18: https://ijisrt.com/assets/upload/files/IJISRT22MAR995.pdf
A23: Part 3: Portfolio Analysis | B23: https://finance.yahoo.com/quote/TATAELXSI.NS/history/?guccounter=1&guce_referrer=aHR0cHM6Ly93d3cuZ29vZ2xlLmNvbS8&guce_referrer_sig=AQAAAIdCXqiH3EBPXgcBiLRxvbrmIrJYHQ_8okBuuDY1QbviIcAGEThA5yGRHCz9h_6fCG6YDxu78Nfbu2poGzkxTxMliFdX_AKozWh2cqzBSbpuyQEuafAiorwf0dhkpEgp_noMLCy9xbLuh7nkE_F77jPGRjdY4xKa1Da3LLm1_Zn-&period1=1648771200&period2=1764374400
B24: https://finance.yahoo.com/quote/RELIANCE.NS/history/?period1=1648771200&period2=1764374400
B25: https://finance.yahoo.com/quote/HDFCBANK.NS/history/?period1=1648771200&period2=1764374400
B26: https://finance.yahoo.com/quote/INFY.NS/history/?period1=1648771200&period2=1764374400
B27: https://finance.yahoo.com/quote/TRENT.NS/history/?period1=1648771200&period2=1764374400
B28: https://finance.yahoo.com/quote/%5ENSEI/history/?period1=1648771200&period2=1764374400
A34: Balance sheet of Tata Elxsi for the last 2 yrs | E34: Income statement of the company for the last 2 yrs | I34: Cashflow statement of the company for the last 2 yrs
A35: Items | B35: FY 2024-25 (₹ Lakhs) | C35: FY 2023-24 (₹ Lakhs) | E35: Items | F35: FY 2024-25 (₹ Lakhs) | G35: FY 2023-24 (₹ Lakhs) | I35: Items | J35: FY 2024-25 (₹ Lakhs) | K35: FY 2023-24 (₹ Lakhs) | M35: date | N35: close | O35: open | P35: high | Q35: low | R35: volume
A36: ASSETS | E36: Revenue from Operations | F36: 372904.83 | G36: 355214.57 | I36: OPERATING ACTIVITIES | M36: 2024-11-29T00:00:00+05:30 | N36: 6670.75 | O36: 6769.9 | P36: 6779.3 | Q36: 6654.3 | R36: 144216
A37: Non-Current Assets | E37: Other Income (Net) | F37: 17931.15 | G37: 12195.18 | I37: Profit for the Year | J37: 78493.68 | K37: 79223.79 | M37: 2024-12-02T00:00:00+05:30 | N37: 6712.95 | O37: 6670.75 | P37: 6775 | Q37: 6613 | R37: 101706
A38: Property, Plant & Equipment | B38: 15411.48 | C38: 19225.5 | E38: Total Income | F38: 390835.98 | G38: 367409.75 | I38: Tax Expense | J38: 24346.72 | K38: 25643.81 | M38: 2024-12-03T00:00:00+05:30 | N38: 7098.55 | O38: 6750.05 | P38: 7178 | Q38: 6740 | R38: 1080035
A39: Capital Work-in-Progress | B39: 161.73 | C39: 215.43 | I39: Depreciation & Amortisation | J39: 10487.08 | K39: 9944.94 | M39: 2024-12-04T00:00:00+05:30 | N39: 7138.95 | O39: 7124.25 | P39: 7199 | Q39: 7060.4 | R39: 248591
A40: Right of Use Assets | B40: 15507.45 | C40: 19028.05 | E40: Cost of Materials Consumed | F40: 23866.29 | G40: 19406.57 | I40: Share Based Payment Transactions | J40: 1006.93 | K40: 1502.31 | M40: 2024-12-05T00:00:00+05:30 | N40: 7367.75 | O40: 7200 | P40: 7474 | Q40: 7151 | R40: 548868
A41: Intangible Assets | B41: 884.96 | C41: 1344.12 | E41: Changes in Inventories | F41: 110.71 | G41: -72.09 | I41: Interest Income | J41: -11649.15 | K41: -9333.34 | M41: 2024-12-06T00:00:00+05:30 | N41: 7396.45 | O41: 7385.55 | P41: 7429 | Q41: 7324.45 | R41: 169740
A42: Financial Assets - Investments | B42: 0 | C42: 0 | E42: Employee Benefits Expense | F42: 204642.7 | G42: 190959.56 | I42: Finance Costs | J42: 1898.14 | K42: 2026.07 | M42: 2024-12-09T00:00:00+05:30 | N42: 7356 | O42: 7400 | P42: 7460 | Q42: 7320 | R42: 130211
A43: Financial Assets - Other Financial Assets | B43: 39638.81 | C43: 19431.59 | E43: Finance Costs | F43: 1898.14 | G43: 2026.07 | I43: Provision for Doubtful Debts | J43: 584.28 | K43: 16.67 | M43: 2024-12-10T00:00:00+05:30 | N43: 7403.15 | O43: 7325 | P43: 7417.15 | Q43: 7325 | R43: 164865
A44: Deferred Tax Assets (Net) | B44: 3762.62 | C44: 2386.9 | E44: Depreciation & Amortisation | F44: 10487.08 | G44: 9944.94 | I44: Other Adjustments | J44: 1847.8 | K44: 1476.98 | M44: 2024-12-11T00:00:00+05:30 | N44: 7350.25 | O44: 7410 | P44: 7415 | Q44: 7326.65 | R44: 117885
A45: Tax Assets (Net) | B45: 3375.24 | C45: 3239.18 | E45: Other Expenses | F45: 46990.66 | G45: 40277.1 | I45: Operating Profit Before WC Changes | J45: 106015.48 | K45: 109433.57 | M45: 2024-12-12T00:00:00+05:30 | N45: 7319.7 | O45: 7360.05 | P45: 7448.95 | Q45: 7286.5 | R45: 236072
A46: Other Non-Current Assets | B46: 79.65 | C46: 155.31 | E46: Total Expenses | F46: 287995.58 | G46: 262542.15 | I46: Changes in Working Capital | J46: -2817.79 | K46: -13310.24 | M46: 2024-12-13T00:00:00+05:30 | N46: 7364.4 | O46: 7314 | P46: 7414 | Q46: 7211.95 | R46: 170937
A47: Total Non-Current Assets | B47: 78821.94 | C47: 65026.08 | E47: Profit Before Tax | F47: 102840.4 | G47: 104867.6 | I47: Cash Generated from Operations | J47: 103591.01 | K47: 95923.17 | M47: 2024-12-16T00:00:00+05:30 | N47: 7357 | O47: 7372.5 | P47: 7424.35 | Q47: 7317.35 | R47: 76612
E48: Tax Expense | I48: Income Tax Paid (Net) | J48: -22393.32 | K48: -25799.84 | M48: 2024-12-17T00:00:00+05:30 | N48: 7273.65 | O48: 7352 | P48: 7400 | Q48: 7232.6 | R48: 135615
A49: Current Assets | E49: Current Tax Expense | F49: 25466.42 | G49: 26206 | I49: Net Cash from Operating Activities | J49: 81197.69 | K49: 70123.33 | M49: 2024-12-18T00:00:00+05:30 | N49: 7230.55 | O49: 7265 | P49: 7363.5 | Q49: 7214.55 | R49: 159943
A50: Inventories | B50: 0 | C50: 110.71 | E50: Deferred Tax Expense | F50: -1119.7 | G50: -562.19 | M50: 2024-12-19T00:00:00+05:30 | N50: 7235.3 | O50: 7150 | P50: 7308.4 | Q50: 7095.05 | R50: 134846
A51: Trade Receivables - Billed | B51: 80185.31 | C51: 82774.7 | E51: Total Tax Expense | F51: 24346.72 | G51: 25643.81 | I51: INVESTING ACTIVITIES | M51: 2024-12-20T00:00:00+05:30 | N51: 6921.6 | O51: 7301.05 | P51: 7325 | Q51: 6900 | R51: 258016
A52: Trade Receivables - Unbilled | B52: 16967.27 | C52: 14384.14 | E52: Net Profit for the Year | F52: 78493.68 | G52: 79223.79 | I52: Acquisition of PPE & Intangibles | J52: 1634.17 | K52: 8301.53 | M52: 2024-12-23T00:00:00+05:30 | N52: 6900.75 | O52: 7037.7 | P52: 7037.7 | Q52: 6825 | R52: 113431
A53: Cash and Cash Equivalents | B53: 13527.66 | C53: 13324.29 | I53: Proceeds from Sale of Assets | J53: 17.42 | K53: 1.78 | M53: 2024-12-24T00:00:00+05:30 | N53: 6857.75 | O53: 6930 | P53: 7015 | Q53: 6828.05 | R53: 150784
A54: Bank Balances (Other) | B54: 147111.67 | C54: 125922.8 | E54: Other Comprehensive Income - Remeasurement of Defined Benefit Plans | F54: -732.67 | G54: -1533.54 | I54: Investment in Bank Deposits | J54: -274460 | K54: -171500 | M54: 2024-12-26T00:00:00+05:30 | N54: 6896.2 | O54: 6865 | P54: 6918.5 | Q54: 6764.4 | R54: 122161
A55: Loans Receivable | B55: 372.06 | C55: 302.45 | E55: Tax on OCI | F55: 256.02 | G55: 535.88 | I55: Proceeds from Redemption of Deposits | J55: 237050 | K55: 144050 | M55: 2024-12-27T00:00:00+05:30 | N55: 6886.35 | O55: 6920 | P55: 6974.8 | Q55: 6831 | R55: 89937
A56: Other Financial Assets (Current) | B56: 2435.88 | C56: 1836.63 | E56: Other Comprehensive Loss for the year, net of income tax | F56: -476.65 | G56: -997.66 | I56: Interest Received | J56: 8198.63 | K56: 8735.52 | M56: 2024-12-30T00:00:00+05:30 | N56: 6925.55 | O56: 6881 | P56: 6965.7 | Q56: 6814.05 | R56: 112066
A57: Other Current Assets | B57: 19149.97 | C57: 15016.36 | E57: Total Comprehensive Income for the Year | F57: 78017.03 | G57: 78226.13 | I57: Net Cash Used in Investing Activities | J57: -30828.12 | K57: -27014.23 | M57: 2024-12-31T00:00:00+05:30 | N57: 6796.55 | O57: 6906.3 | P57: 6925.55 | Q57: 6724.1 | R57: 104133
A58: Total Current Assets | B58: 279749.82 | C58: 253672.08 | E58: Eearnings per equity share( in ₹ ) | M58: 2025-01-01T00:00:00+05:30 | N58: 6743.75 | O58: 6810.5 | P58: 6840 | Q58: 6711.6 | R58: 91883
A59: TOTAL ASSETS | B59: 358571.76 | C59: 318698.16 | E59: Basic EPS (₹) | F59: 126.03 | G59: 127.21 | I59: FINANCING ACTIVITIES | M59: 2025-01-02T00:00:00+05:30 | N59: 6705.25 | O59: 6743.75 | P59: 6779.95 | Q59: 6508.2 | R59: 381285
E60: Diluted EPS (₹) | F60: 126.01 | G60: 127.18 | I60: Repayment of Lease Liabilities | J60: 6122.41 | K60: 4976.76 | M60: 2025-01-03T00:00:00+05:30 | N60: 6647.55 | O60: 6710 | P60: 6759.8 | Q60: 6607 | R60: 227250
A61: EQUITY AND LIABILITIES | I61: Finance Cost Paid | J61: 144.37 | K61: 66.53 | M61: 2025-01-06T00:00:00+05:30 | N61: 6486.45 | O61: 6690 | P61: 6710.9 | Q61: 6470.15 | R61: 175457
A62: Equity | I62: Proceeds from Exercise of Share Options | J62: 0.81 | K62: 0 | M62: 2025-01-07T00:00:00+05:30 | N62: 6542.35 | O62: 6540 | P62: 6577.75 | Q62: 6422.5 | R62: 208512
A63: Equity Share Capital | B63: 6228.41 | C63: 6227.64 | I63: Dividends Paid | J63: 43593.51 | K63: 37739.52 | M63: 2025-01-08T00:00:00+05:30 | N63: 6473.5 | O63: 6575 | P63: 6591.85 | Q63: 6338 | R63: 380865
A64: Other Equity | B64: 279768.48 | C64: 244337.99 | I64: Net Cash Used in Financing Activities | J64: -49859.48 | K64: -42782.81 | M64: 2025-01-09T00:00:00+05:30 | N64: 6439.95 | O64: 6525 | P64: 6635 | Q64: 6425 | R64: 346979
A65: Total Equity | B65: 285996.89 | C65: 250565.63 | M65: 2025-01-10T00:00:00+05:30 | N65: 6000.6 | O65: 5950 | P65: 6200 | Q65: 5921 | R65: 1431569
I66: Net Increase in Cash | J66: 510.09 | K66: 326.29 | M66: 2025-01-13T00:00:00+05:30 | N66: 5941.6 | O66: 5975 | P66: 6088.95 | Q66: 5920 | R66: 368080
A67: Non-Current Liabilities | I67: Cash at Beginning of Year | J67: 13324.29 | K67: 13389.17 | M67: 2025-01-14T00:00:00+05:30 | N67: 6084.8 | O67: 5959.9 | P67: 6125 | Q67: 5959.9 | R67: 230728
A68: Lease Liabilities (Non-Current) | B68: 13931.26 | C68: 18118.9 | I68: Exchange Difference on Cash | J68: -306.71 | K68: -391.17 | M68: 2025-01-15T00:00:00+05:30 | N68: 6115.75 | O68: 6093.9 | P68: 6135.05 | Q68: 6026.6 | R68: 119683
A69: Provisions (Non-Current) | B69: 5675.31 | C69: 5419.99 | I69: Cash at End of Year | J69: 13527.67 | K69: 13324.29 | M69: 2025-01-16T00:00:00+05:30 | N69: 6184.25 | O69: 6140 | P69: 6245.2 | Q69: 6130 | R69: 144322
A70: Total Non-Current Liabilities | B70: 19606.57 | C70: 23538.89 | M70: 2025-01-17T00:00:00+05:30 | N70: 6212.1 | O70: 6190 | P70: 6250.85 | Q70: 6150 | R70: 131996
M71: 2025-01-20T00:00:00+05:30 | N71: 6199.8 | O71: 6218 | P71: 6229.05 | Q71: 6121.45 | R71: 91944
A72: Current Liabilities | M72: 2025-01-21T00:00:00+05:30 | N72: 6153.95 | O72: 6220.2 | P72: 6275 | Q72: 6140 | R72: 87671
A73: Lease Liabilities (Current) | B73: 5297.82 | C73: 4279.24 | M73: 2025-01-22T00:00:00+05:30 | N73: 6167.35 | O73: 6170 | P73: 6178 | Q73: 6060.7 | R73: 124965
A74: Trade Payables - MSME | B74: 1150.71 | C74: 414.53 | M74: 2025-01-23T00:00:00+05:30 | N74: 6353.95 | O74: 6167.5 | P74: 6425 | Q74: 6150 | R74: 221641
A75: Trade Payables - Others | B75: 11150.21 | C75: 8149.37 | M75: 2025-01-24T00:00:00+05:30 | N75: 6372.7 | O75: 6353.95 | P75: 6392.95 | Q75: 6290 | R75: 108179
A76: Other Financial Liabilities (Current) | B76: 9210.61 | C76: 10352.34 | M76: 2025-01-27T00:00:00+05:30 | N76: 6156.05 | O76: 6319.95 | P76: 6327.55 | Q76: 6128.15 | R76: 161634
A77: Other Current Liabilities | B77: 12563.46 | C77: 12081.43 | M77: 2025-01-28T00:00:00+05:30 | N77: 6125.4 | O77: 6150 | P77: 6203.9 | Q77: 6078.05 | R77: 148138
A78: Provisions (Current) | B78: 4915.87 | C78: 3846.27 | M78: 2025-01-29T00:00:00+05:30 | N78: 6173.85 | O78: 6129.2 | P78: 6221.95 | Q78: 6094.95 | R78: 143522
A79: Current Tax Liabilities (Net) | B79: 8679.62 | C79: 5470.46 | M79: 2025-01-30T00:00:00+05:30 | N79: 6135.7 | O79: 6195 | P79: 6215.95 | Q79: 6090 | R79: 138349
A80: Total Current Liabilities | B80: 52968.3 | C80: 44593.64 | M80: 2025-01-31T00:00:00+05:30 | N80: 6336 | O80: 6145 | P80: 6350 | Q80: 6130.1 | R80: 122121
A81: TOTAL EQUITY AND LIABILITIES | B81: 358571.76 | C81: 318698.16 | M81: 2025-02-01T00:00:00+05:30 | N81: 6381.25 | O81: 6370 | P81: 6400 | Q81: 6269.05 | R81: 80662
M82: 2025-02-03T00:00:00+05:30 | N82: 6396.25 | O82: 6330 | P82: 6420 | Q82: 6250.7 | R82: 71348
M83: 2025-02-04T00:00:00+05:30 | N83: 6371.1 | O83: 6415 | P83: 6467 | Q83: 6312.65 | R83: 87790
M84: 2025-02-05T00:00:00+05:30 | N84: 6384.5 | O84: 6371.1 | P84: 6443.95 | Q84: 6345.05 | R84: 66079
M85: 2025-02-06T00:00:00+05:30 | N85: 6421.9 | O85: 6400 | P85: 6478.15 | Q85: 6372.05 | R85: 82289
M86: 2025-02-07T00:00:00+05:30 | N86: 6436.6 | O86: 6421.9 | P86: 6455.25 | Q86: 6332.05 | R86: 64931
M87: 2025-02-10T00:00:00+05:30 | N87: 6377.4 | O87: 6415 | P87: 6425 | Q87: 6335.25 | R87: 60322
M88: 2025-02-11T00:00:00+05:30 | N88: 6116.75 | O88: 6399.95 | P88: 6399.95 | Q88: 6100 | R88: 100616
M89: 2025-02-12T00:00:00+05:30 | N89: 6154.05 | O89: 6110 | P89: 6170 | Q89: 6032.5 | R89: 130838
M90: 2025-02-13T00:00:00+05:30 | N90: 6134.35 | O90: 6199.95 | P90: 6199.95 | Q90: 6082 | R90: 135495
M91: 2025-02-14T00:00:00+05:30 | N91: 6174 | O91: 6145.05 | P91: 6225 | Q91: 6081.05 | R91: 130626
M92: 2025-02-17T00:00:00+05:30 | N92: 6146.85 | O92: 6156 | P92: 6176.35 | Q92: 6042.85 | R92: 73576
M93: 2025-02-18T00:00:00+05:30 | N93: 6097.45 | O93: 6146.85 | P93: 6175.65 | Q93: 6045.05 | R93: 72228
... M283: 2025-11-28T00:00:00+05:30 | N283: 5158.5 | O283: 5205.5 | P283: 5206 | Q283: 5150 | R283: 136784
R284: =AVERAGE(R36:R283) -> 233084.19
